{"dt":"11/11/2020","ht":"17:00:47","tf":"s","s":44,"st":44,"pst":" 100,00","snt":0,"psnt":"   0,00","si":44,"psi":" 100,00","sni":0,"psni":"   0,00","sa":44,"psa":" 100,00","sna":0,"psna":"   0,00","e":10939,"ea":10939,"pea":" 100,00","ena":0,"pena":"   0,00","esi":10939,"pesi":" 100,00","esni":0,"pesni":"   0,00","c":9320,"pc":"  85,20","a":1619,"pa":"  14,80","tv":9320,"vvc":6399,"pvvc":"  68,66","vscv":0,"vb":1190,"pvb":"  12,77","tvn":1731,"ptvn":"  18,57","vn":1731,"pvn":" 100,00","vnt":0,"pvnt":"   0,00","vp":0,"pvp":"   0,00","vv":6399,"pvv":" 100,00","van":0,"pvan":"   0,00","vansj":0,"pvansj":"   0,00","vnom":6399,"pvnom":" 100,00","cand":[{"seq":3,"sqcand":140000006949,"n":21,"nm":"CANDIDATO 21","cc":"P21 -  P21 / P78 / P12 / P13 / P14 / P24 / P71 / P91","nv":"CANDIDATO 21 1","e":"n","vap":1437,"pvap":"  22,46","st":"Não eleito","dvt":"Válido"},{"seq":2,"sqcand":140000017384,"n":46,"nm":"CANDIDATO 46","cc":"P46 -  P46 / P26 / P15 / P19","nv":"CANDIDATO 46 1","e":"n","vap":1651,"pvap":"  25,80","st":"Não eleito","dvt":"Válido"},{"seq":4,"sqcand":140000012552,"n":23,"nm":"CANDIDATO 23","cc":"P23 -  P23 / P56 / P16 / P66 / P29","nv":"CANDIDATO 23 1","e":"n","vap":1297,"pvap":"  20,27","st":"Não eleito","dvt":"Válido"},{"seq":1,"sqcand":140000011508,"n":11,"nm":"CANDIDATO 11","cc":"P11 -  P11 / P45 / P52","nv":"CANDIDATO 11 1","e":"s","vap":2014,"pvap":"  31,47","st":"Eleito","dvt":"Válido"}],"ele":8334,"tpabr":"mu","cdabr":"04316","carper":11,"t":1,"f":"s","dv":"s","esae":"n","mnae":"","v":1}