{"ele":8707,"cdabr":"71390","nmabr":"SEVERÍNIA","t":1,"f":"S","s":"N","dg":"13/10/2020","hg":"20:03:18","v":"004","br":{"nm":"Brasil","uf":[{"sg":"SP","nm":"SÃO PAULO","mun":[{"cd":"71390","nm":"SEVERÍNIA","c":"N","s":36,"e":12501,"tzon":1,"zon":[{"cd":"0080","s":36,"e":12501}]}]}]},"carg":{"cd":13,"nmn":"Vereador","nmm":"Vereador","nmf":"Vereadora","nv":11,"col":[{"n":250000282978,"nm":"COLIGACAO 250000282978","tp":"P","com":"P46","par":[{"n":46,"sg":" P46 ","nm":"PARTIDO 46","cand":[{"sqcand":250002350195,"n":46011,"nm":"CANDIDATO 46011","nmu":"CANDIDATO 46011","s":"M","dt":"19/08/1929","dvt":"Válido"},{"sqcand":250002350198,"n":46014,"nm":"CANDIDATO 46014","nmu":"CANDIDATO 46014","s":"M","dt":"13/08/1924","dvt":"Válido"},{"sqcand":250002350188,"n":46004,"nm":"CANDIDATO 46004","nmu":"CANDIDATO 46004","s":"F","dt":"09/04/1929","dvt":"Válido"},{"sqcand":250002350186,"n":46002,"nm":"CANDIDATO 46002","nmu":"CANDIDATO 46002","s":"F","dt":"03/07/1929","dvt":"Válido"},{"sqcand":250002350187,"n":46003,"nm":"CANDIDATO 46003","nmu":"CANDIDATO 46003","s":"F","dt":"26/08/1925","dvt":"Válido"},{"sqcand":250002350190,"n":46006,"nm":"CANDIDATO 46006","nmu":"CANDIDATO 46006","s":"M","dt":"02/03/1929","dvt":"Válido"},{"sqcand":250002350196,"n":46012,"nm":"CANDIDATO 46012","nmu":"CANDIDATO 46012","s":"M","dt":"07/12/1929","dvt":"Válido"},{"sqcand":250002350199,"n":46015,"nm":"CANDIDATO 46015","nmu":"CANDIDATO 46015","s":"M","dt":"04/07/1929","dvt":"Válido"},{"sqcand":250002350185,"n":46001,"nm":"CANDIDATO 46001","nmu":"CANDIDATO 46001","s":"F","dt":"22/07/1929","dvt":"Válido"},{"sqcand":250002350191,"n":46007,"nm":"CANDIDATO 46007","nmu":"CANDIDATO 46007","s":"M","dt":"18/01/1925","dvt":"Válido"},{"sqcand":250002350193,"n":46009,"nm":"CANDIDATO 46009","nmu":"CANDIDATO 46009","s":"M","dt":"29/06/1929","dvt":"Válido"},{"sqcand":250002350197,"n":46013,"nm":"CANDIDATO 46013","nmu":"CANDIDATO 46013","s":"M","dt":"17/08/1929","dvt":"Válido"},{"sqcand":250002350189,"n":46005,"nm":"CANDIDATO 46005","nmu":"CANDIDATO 46005","s":"M","dt":"13/03/1977","dvt":"Válido"},{"sqcand":250002350192,"n":46008,"nm":"CANDIDATO 46008","nmu":"CANDIDATO 46008","s":"M","dt":"22/08/1925","dvt":"Válido"},{"sqcand":250002350194,"n":46010,"nm":"CANDIDATO 46010","nmu":"CANDIDATO 46010","s":"M","dt":"01/12/1925","dvt":"Válido"}]}]},{"n":250000282976,"nm":"COLIGACAO 250000282976","tp":"P","com":"P41","par":[{"n":41,"sg":" P41 ","nm":"PARTIDO 41","cand":[{"sqcand":250002350166,"n":41010,"nm":"CANDIDATO 41010","nmu":"CANDIDATO 41010","s":"M","dt":"06/06/1928","dvt":"Válido"},{"sqcand":250002350167,"n":41011,"nm":"CANDIDATO 41011","nmu":"CANDIDATO 41011","s":"M","dt":"11/02/1993","dvt":"Válido"},{"sqcand":250002350158,"n":41002,"nm":"CANDIDATO 41002","nmu":"CANDIDATO 41002","s":"F","dt":"23/07/1929","dvt":"Válido"},{"sqcand":250002350159,"n":41003,"nm":"CANDIDATO 41003","nmu":"CANDIDATO 41003","s":"F","dt":"18/08/1929","dvt":"Válido"},{"sqcand":250002350164,"n":41008,"nm":"CANDIDATO 41008","nmu":"CANDIDATO 41008","s":"M","dt":"12/09/1929","dvt":"Válido"},{"sqcand":250002350168,"n":41012,"nm":"CANDIDATO 41012","nmu":"CANDIDATO 41012","s":"M","dt":"16/10/1920","dvt":"Válido"},{"sqcand":250002350160,"n":41004,"nm":"CANDIDATO 41004","nmu":"CANDIDATO 41004","s":"M","dt":"13/03/1989","dvt":"Válido"},{"sqcand":250002350161,"n":41005,"nm":"CANDIDATO 41005","nmu":"CANDIDATO 41005","s":"M","dt":"01/03/1929","dvt":"Válido"},{"sqcand":250002350157,"n":41001,"nm":"CANDIDATO 41001","nmu":"CANDIDATO 41001","s":"F","dt":"07/08/1966","dvt":"Válido"},{"sqcand":250002350162,"n":41006,"nm":"CANDIDATO 41006","nmu":"CANDIDATO 41006","s":"M","dt":"03/01/1928","dvt":"Válido"},{"sqcand":250002350163,"n":41007,"nm":"CANDIDATO 41007","nmu":"CANDIDATO 41007","s":"M","dt":"10/03/1973","dvt":"Válido"},{"sqcand":250002350165,"n":41009,"nm":"CANDIDATO 41009","nmu":"CANDIDATO 41009","s":"M","dt":"13/04/1987","dvt":"Válido"},{"sqcand":250002350169,"n":41013,"nm":"CANDIDATO 41013","nmu":"CANDIDATO 41013","s":"M","dt":"25/01/1925","dvt":"Válido"}]}]},{"n":250000282977,"nm":"COLIGACAO 250000282977","tp":"P","com":"P44","par":[{"n":44,"sg":" P44 ","nm":"PARTIDO 44","cand":[{"sqcand":250002350178,"n":44009,"nm":"CANDIDATO 44009","nmu":"CANDIDATO 44009","s":"M","dt":"26/12/1926","dvt":"Válido"},{"sqcand":250002350181,"n":44012,"nm":"CANDIDATO 44012","nmu":"CANDIDATO 44012","s":"M","dt":"10/02/1929","dvt":"Válido"},{"sqcand":250002350172,"n":44003,"nm":"CANDIDATO 44003","nmu":"CANDIDATO 44003","s":"F","dt":"26/08/1927","dvt":"Válido"},{"sqcand":250002350173,"n":44004,"nm":"CANDIDATO 44004","nmu":"CANDIDATO 44004","s":"F","dt":"17/12/1929","dvt":"Válido"},{"sqcand":250002350174,"n":44005,"nm":"CANDIDATO 44005","nmu":"CANDIDATO 44005","s":"M","dt":"16/10/1929","dvt":"Válido"},{"sqcand":250002350176,"n":44007,"nm":"CANDIDATO 44007","nmu":"CANDIDATO 44007","s":"M","dt":"01/09/1920","dvt":"Válido"},{"sqcand":250002350179,"n":44010,"nm":"CANDIDATO 44010","nmu":"CANDIDATO 44010","s":"M","dt":"26/07/1929","dvt":"Válido"},{"sqcand":250002350183,"n":44014,"nm":"CANDIDATO 44014","nmu":"CANDIDATO 44014","s":"M","dt":"15/09/1951","dvt":"Válido"},{"sqcand":250002350184,"n":44015,"nm":"CANDIDATO 44015","nmu":"CANDIDATO 44015","s":"M","dt":"20/07/1928","dvt":"Válido"},{"sqcand":250002350177,"n":44008,"nm":"CANDIDATO 44008","nmu":"CANDIDATO 44008","s":"M","dt":"03/04/1922","dvt":"Válido"},{"sqcand":250002350180,"n":44011,"nm":"CANDIDATO 44011","nmu":"CANDIDATO 44011","s":"M","dt":"01/12/1927","dvt":"Válido"},{"sqcand":250002350182,"n":44013,"nm":"CANDIDATO 44013","nmu":"CANDIDATO 44013","s":"M","dt":"10/08/1967","dvt":"Válido"},{"sqcand":250002350170,"n":44001,"nm":"CANDIDATO 44001","nmu":"CANDIDATO 44001","s":"F","dt":"08/12/1955","dvt":"Válido"},{"sqcand":250002350171,"n":44002,"nm":"CANDIDATO 44002","nmu":"CANDIDATO 44002","s":"F","dt":"19/01/1929","dvt":"Válido"},{"sqcand":250002350175,"n":44006,"nm":"CANDIDATO 44006","nmu":"CANDIDATO 44006","s":"M","dt":"10/04/1975","dvt":"Válido"}]}]}]}}