{"dt":"09/10/2020","ht":"17:28:01","tf":"s","s":80,"st":80,"pst":" 100,00","snt":0,"psnt":"   0,00","si":80,"psi":" 100,00","sni":0,"psni":"   0,00","sa":80,"psa":" 100,00","sna":0,"psna":"   0,00","e":21382,"ea":21382,"pea":" 100,00","ena":0,"pena":"   0,00","esi":21382,"pesi":" 100,00","esni":0,"pesni":"   0,00","c":18089,"pc":"  84,60","a":3293,"pa":"  15,40","tv":18089,"vscv":0,"vb":627,"pvb":"   3,46","tvn":459,"ptvn":"   2,54","vn":459,"pvn":" 100,00","vnt":0,"pvnt":"00.00","vp":0,"pvp":"00.00","vv":15920,"pvv":"  88,01","vl":1671,"pvl":"  10,50","van":0,"pvan":"00.00","vansj":1083,"pvansj":"   5,99","vnom":14249,"pvnom":"  89,50","cand":[{"seq":17,"sqcand":170002244248,"n":20007,"nm":"CANDIDATO 20007","cc":"P20","nv":" ","e":"n","vap":509,"pvap":"   2,81","st":"Suplente","dvt":"Válido"},{"seq":20,"sqcand":170002244257,"n":15006,"nm":"CANDIDATO 15006","cc":"P15","nv":" ","e":"n","vap":1083,"pvap":"   5,99","st":"Não eleito","dvt":"Anulado sub judice"},{"seq":18,"sqcand":170002244249,"n":20008,"nm":"CANDIDATO 20008","cc":"P20","nv":" ","e":"n","vap":493,"pvap":"   2,73","st":"Suplente","dvt":"Válido"},{"seq":19,"sqcand":170002244261,"n":15010,"nm":"CANDIDATO 15010","cc":"P15","nv":" ","e":"n","vap":385,"pvap":"   2,13","st":"Suplente","dvt":"Válido"},{"seq":9,"sqcand":170002244259,"n":15008,"nm":"CANDIDATO 15008","cc":"P15","nv":" ","e":"n","vap":695,"pvap":"   3,84","st":"Suplente","dvt":"Válido"},{"seq":13,"sqcand":170002244250,"n":20009,"nm":"CANDIDATO 20009","cc":"P20","nv":" ","e":"n","vap":617,"pvap":"   3,41","st":"Suplente","dvt":"Válido"},{"seq":5,"sqcand":170002244247,"n":20006,"nm":"CANDIDATO 20006","cc":"P20","nv":" ","e":"s","vap":881,"pvap":"   4,87","st":"Eleito","dvt":"Válido"},{"seq":14,"sqcand":170002244256,"n":15005,"nm":"CANDIDATO 15005","cc":"P15","nv":" ","e":"n","vap":608,"pvap":"   3,36","st":"Suplente","dvt":"Válido"},{"seq":6,"sqcand":170002244245,"n":20004,"nm":"CANDIDATO 20004","cc":"P20","nv":" ","e":"s","vap":836,"pvap":"   4,62","st":"Eleito","dvt":"Válido"},{"seq":7,"sqcand":170002244251,"n":20010,"nm":"CANDIDATO 20010","cc":"P20","nv":" ","e":"s","vap":709,"pvap":"   3,92","st":"Eleito","dvt":"Válido"},{"seq":15,"sqcand":170002244258,"n":15007,"nm":"CANDIDATO 15007","cc":"P15","nv":" ","e":"n","vap":601,"pvap":"   3,32","st":"Suplente","dvt":"Válido"},{"seq":11,"sqcand":170002244242,"n":20001,"nm":"CANDIDATO 20001","cc":"P20","nv":" ","e":"n","vap":681,"pvap":"   3,76","st":"Suplente","dvt":"Válido"},{"seq":4,"sqcand":170002244252,"n":15001,"nm":"CANDIDATO 15001","cc":"P15","nv":" ","e":"s","vap":1010,"pvap":"   5,58","st":"Eleito","dvt":"Válido"},{"seq":3,"sqcand":170002244255,"n":15004,"nm":"CANDIDATO 15004","cc":"P15","nv":" ","e":"s","vap":1120,"pvap":"   6,19","st":"Eleito","dvt":"Válido"},{"seq":10,"sqcand":170002244244,"n":20003,"nm":"CANDIDATO 20003","cc":"P20","nv":" ","e":"n","vap":681,"pvap":"   3,76","st":"Suplente","dvt":"Válido"},{"seq":2,"sqcand":170002244260,"n":15009,"nm":"CANDIDATO 15009","cc":"P15","nv":" ","e":"s","vap":1189,"pvap":"   6,57","st":"Eleito","dvt":"Válido"},{"seq":1,"sqcand":170002244254,"n":15003,"nm":"CANDIDATO 15003","cc":"P15","nv":" ","e":"s","vap":1225,"pvap":"   6,77","st":"Eleito","dvt":"Válido"},{"seq":16,"sqcand":170002244243,"n":20002,"nm":"CANDIDATO 20002","cc":"P20","nv":" ","e":"n","vap":562,"pvap":"   3,11","st":"Suplente","dvt":"Válido"},{"seq":12,"sqcand":170002244246,"n":20005,"nm":"CANDIDATO 20005","cc":"P20","nv":" ","e":"n","vap":638,"pvap":"   3,53","st":"Suplente","dvt":"Válido"},{"seq":8,"sqcand":170002244253,"n":15002,"nm":"CANDIDATO 15002","cc":"P15","nv":" ","e":"n","vap":809,"pvap":"   4,47","st":"Suplente","dvt":"Válido"}],"ele":8707,"tpabr":"mu","cdabr":"25712","carper":13,"t":1,"f":"s","dv":"s","esae":"n","mnae":"","v":7}