{"ele":8707,"carper":11,"t":1,"f":"S","esae":"N","mnae":" ","dg":"13/10/2020","hg":"20:04:52","dv":"S","nadf":"rj58343-c0011-e008707-006-f","abr":[{"dt":"09/10/2020","ht":"16:25:00","tf":"N","and":"P","s":26,"st":25,"pst":"  96,15","snt":1,"psnt":"   3,85","si":25,"psi":"  96,15","sni":0,"psni":"   0,00","sa":25,"psa":" 100,00","sna":0,"psna":"   0,00","e":6835,"ea":6835,"pea":" 100,00","ena":0,"pena":"   0,00","esi":6835,"pesi":"  96,15","esni":0,"pesni":"   0,00","c":5821,"pc":"  85,16","a":1014,"pa":"  14,84","tv":5821,"vscv":0,"vb":1028,"pvb":"  17,66","tvn":883,"ptvn":"  15,17","vn":883,"pvn":" 100,00","vnt":0,"pvnt":"   0,00","vp":0,"pvp":"   0,00","vv":2340,"pvv":"  59,85","van":0,"pvan":"   0,00","vansj":1570,"pvansj":"  40,15","vnom":2340,"pvnom":" 100,00","cand":[{"seq":1,"n":11,"e":"N","vap":1095,"pvap":"  18,81","st":""},{"seq":4,"n":15,"e":"N","vap":1570,"pvap":"  26,97","st":""},{"seq":3,"n":46,"e":"N","vap":617,"pvap":"  10,60","st":""},{"seq":2,"n":16,"e":"N","vap":628,"pvap":"  10,79","st":""}],"tpabr":"MU","cdabr":"58343","colig":[{"n":190000276831,"tvtn":1095,"tvtl":0,"tvan":1095,"tval":0},{"n":190000276832,"tvtn":0,"tvtl":0,"tvan":1570,"tval":0},{"n":190000276836,"tvtn":617,"tvtl":0,"tvan":617,"tval":0},{"n":190000276834,"tvtn":628,"tvtl":0,"tvan":628,"tval":0}],"part":[{"n":11,"tvtn":1095,"tvtl":0,"tvan":1095,"tval":0},{"n":12,"tvtn":0,"tvtl":0,"tvan":0,"tval":0},{"n":15,"tvtn":0,"tvtl":0,"tvan":1570,"tval":0},{"n":46,"tvtn":617,"tvtl":0,"tvan":617,"tval":0},{"n":16,"tvtn":628,"tvtl":0,"tvan":628,"tval":0}]},{"dt":"09/10/2020","ht":"16:25:00","tf":"N","and":"P","s":26,"st":25,"pst":"  96,15","snt":1,"psnt":"1","si":25,"psi":"  96,15","sni":0,"psni":"   0,00","sa":25,"psa":" 100,00","sna":0,"psna":"   0,00","e":6835,"ea":6835,"pea":" 100,00","ena":0,"pena":"   0,00","esi":6835,"pesi":"  96,15","esni":0,"pesni":"   0,00","c":5821,"pc":"  85,16","a":1014,"pa":"  14,84","tv":5821,"vscv":0,"vb":1028,"pvb":"  17,66","tvn":883,"ptvn":"  15,17","vn":883,"pvn":" 100,00","vp":0,"pvp":"   0,00","vv":2340,"pvv":"  59,85","van":0,"pvan":"   0,00","vansj":1570,"pvansj":"  40,15","vnom":2340,"pvnom":" 100,00","cand":[{"seq":1,"n":11,"e":"N","vap":1095,"pvap":"  18,81","st":""},{"seq":3,"n":46,"e":"N","vap":617,"pvap":"  10,60","st":""},{"seq":4,"n":15,"e":"N","vap":1570,"pvap":"  26,97","st":""},{"seq":2,"n":16,"e":"N","vap":628,"pvap":"  10,79","st":""}],"tpabr":"ZONA","cdabr":"107"}]}