{"ele":8707,"cdabr":"85596","nmabr":"CACHOEIRA DO SUL","t":1,"f":"S","s":"N","dg":"13/10/2020","hg":"20:04:20","v":"005","br":{"nm":"Brasil","uf":[{"sg":"RS","nm":"RIO GRANDE DO SUL","mun":[{"cd":"85596","nm":"CACHOEIRA DO SUL","c":"N","s":238,"e":69577,"tzon":1,"zon":[{"cd":"0010","s":238,"e":69577}]}]}]},"carg":{"cd":11,"nmn":"Prefeito","nmm":"Prefeito","nmf":"Prefeita","nv":1,"col":[{"n":210000269701,"nm":"COLIGACAO 210000269701","tp":"P","com":"P15","par":[{"n":15,"sg":" P15 ","nm":"PARTIDO 15","cand":[{"sqcand":210002285606,"n":15,"nm":"CANDIDATO 15","nmu":"CANDIDATO 15","s":"M","dt":"02/02/1922","dvt":"Válido","vs":[{"sqcand":210002285607,"nm":"CANDIDATO 15 1","nmu":"CANDIDATO 15 1","tp":"V","sgp":"P15"}]}]}]},{"n":210000269700,"nm":"COLIGACAO 210000269700","tp":"P","com":"P12","par":[{"n":12,"sg":" P12 ","nm":"PARTIDO 12","cand":[{"sqcand":210002285604,"n":12,"nm":"CANDIDATO 12","nmu":"CANDIDATO 12","s":"M","dt":"16/02/1924","dvt":"Válido","vs":[{"sqcand":210002285605,"nm":"CANDIDATO 12 1","nmu":"CANDIDATO 12 1","tp":"V","sgp":"P12"}]}]}]}]}}