{"ele":8707,"cdabr":"10286","nmabr":"JACOBINA DO PIAUÍ","t":1,"f":"S","s":"N","dg":"13/10/2020","hg":"20:04:24","v":"005","br":{"nm":"Brasil","uf":[{"sg":"PI","nm":"PIAUÍ","mun":[{"cd":"10286","nm":"JACOBINA DO PIAUÍ","c":"N","s":24,"e":4575,"tzon":1,"zon":[{"cd":"0038","s":24,"e":4575}]}]}]},"carg":{"cd":11,"nmn":"Prefeito","nmm":"Prefeito","nmf":"Prefeita","nv":1,"col":[{"n":180000272722,"nm":"COLIGACAO 180000272722","tp":"P","com":"P12","par":[{"n":12,"sg":" P12 ","nm":"PARTIDO 12","cand":[{"sqcand":180002296541,"n":12,"nm":"CANDIDATO 12","nmu":"CANDIDATO 12","s":"M","dt":"12/07/1928","dvt":"Válido","vs":[{"sqcand":180002296542,"nm":"CANDIDATO 12 1","nmu":"CANDIDATO 12 1","tp":"V","sgp":"P12"}]}]}]},{"n":180000272726,"nm":"COLIGACAO 180000272726","tp":"P","com":"P34","par":[{"n":34,"sg":" P34 ","nm":"PARTIDO 34","cand":[{"sqcand":180002296563,"n":34,"nm":"CANDIDATO 34","nmu":"CANDIDATO 34","s":"M","dt":"25/08/1923","dvt":"Válido","vs":[{"sqcand":180002296564,"nm":"CANDIDATO 34 1","nmu":"CANDIDATO 34 1","tp":"V","sgp":"P34"}]}]}]}]}}