{"ele":8707,"cdabr":"12190","nmabr":"TERESINA","t":1,"f":"S","dg":"13/10/2020","hg":"20:04:24","car":{"cd":11,"nm":"Prefeito","scv":"N","cand":[{"n":12,"nmu":"CANDIDATO 12","c":"#a9a9a9","sgp":"P12","ap":[{"dataHoraApuracao":"09/10/2020 12:51:00","da":"09/10/2020","ha":"12:51:00","vap":410,"tvap":1651,"pvap":"24,83"},{"dataHoraApuracao":"09/10/2020 12:52:00","da":"09/10/2020","ha":"12:52:00","vap":4267,"tvap":14651,"pvap":"29,12"},{"dataHoraApuracao":"09/10/2020 12:53:00","da":"09/10/2020","ha":"12:53:00","vap":6763,"tvap":23386,"pvap":"28,91"},{"dataHoraApuracao":"09/10/2020 13:02:00","da":"09/10/2020","ha":"13:02:00","vap":7477,"tvap":25449,"pvap":"29,38"},{"dataHoraApuracao":"09/10/2020 13:03:00","da":"09/10/2020","ha":"13:03:00","vap":11886,"tvap":39017,"pvap":"30,46"},{"dataHoraApuracao":"09/10/2020 13:04:00","da":"09/10/2020","ha":"13:04:00","vap":13994,"tvap":44593,"pvap":"31,38"},{"dataHoraApuracao":"09/10/2020 13:16:00","da":"09/10/2020","ha":"13:16:00","vap":14563,"tvap":46770,"pvap":"31,13"},{"dataHoraApuracao":"09/10/2020 13:17:00","da":"09/10/2020","ha":"13:17:00","vap":17144,"tvap":53311,"pvap":"32,15"},{"dataHoraApuracao":"09/10/2020 13:18:00","da":"09/10/2020","ha":"13:18:00","vap":17148,"tvap":53386,"pvap":"32,12"},{"dataHoraApuracao":"09/10/2020 13:26:00","da":"09/10/2020","ha":"13:26:00","vap":17150,"tvap":53571,"pvap":"32,01"},{"dataHoraApuracao":"09/10/2020 13:28:00","da":"09/10/2020","ha":"13:28:00","vap":17154,"tvap":53629,"pvap":"31,98"},{"dataHoraApuracao":"09/10/2020 13:29:00","da":"09/10/2020","ha":"13:29:00","vap":17169,"tvap":53672,"pvap":"31,98"},{"dataHoraApuracao":"09/10/2020 13:58:00","da":"09/10/2020","ha":"13:58:00","vap":17276,"tvap":53947,"pvap":"32,02"},{"dataHoraApuracao":"09/10/2020 15:01:00","da":"09/10/2020","ha":"15:01:00","vap":17962,"tvap":56074,"pvap":"32,03"},{"dataHoraApuracao":"09/10/2020 15:02:00","da":"09/10/2020","ha":"15:02:00","vap":18643,"tvap":58246,"pvap":"32"},{"dataHoraApuracao":"09/10/2020 15:03:00","da":"09/10/2020","ha":"15:03:00","vap":24084,"tvap":73216,"pvap":"32,89"},{"dataHoraApuracao":"09/10/2020 15:05:00","da":"09/10/2020","ha":"15:05:00","vap":27522,"tvap":86235,"pvap":"31,91"},{"dataHoraApuracao":"09/10/2020 15:06:00","da":"09/10/2020","ha":"15:06:00","vap":29017,"tvap":90407,"pvap":"32,09"},{"dataHoraApuracao":"09/10/2020 15:07:00","da":"09/10/2020","ha":"15:07:00","vap":29118,"tvap":90595,"pvap":"32,14"},{"dataHoraApuracao":"09/10/2020 15:08:00","da":"09/10/2020","ha":"15:08:00","vap":29120,"tvap":90878,"pvap":"32,04"},{"dataHoraApuracao":"09/10/2020 15:09:00","da":"09/10/2020","ha":"15:09:00","vap":30954,"tvap":96799,"pvap":"31,97"},{"dataHoraApuracao":"09/10/2020 15:10:00","da":"09/10/2020","ha":"15:10:00","vap":37512,"tvap":113629,"pvap":"33,01"},{"dataHoraApuracao":"09/10/2020 15:11:00","da":"09/10/2020","ha":"15:11:00","vap":38612,"tvap":116114,"pvap":"33,25"},{"dataHoraApuracao":"09/10/2020 15:27:00","da":"09/10/2020","ha":"15:27:00","vap":38643,"tvap":116263,"pvap":"33,23"},{"dataHoraApuracao":"13/10/2020 14:39:00","da":"13/10/2020","ha":"14:39:00","vap":41303,"tvap":122792,"pvap":"33,63"},{"dataHoraApuracao":"13/10/2020 14:40:00","da":"13/10/2020","ha":"14:40:00","vap":44423,"tvap":132393,"pvap":"33,55"},{"dataHoraApuracao":"13/10/2020 14:41:00","da":"13/10/2020","ha":"14:41:00","vap":49248,"tvap":147359,"pvap":"33,42"},{"dataHoraApuracao":"13/10/2020 14:42:00","da":"13/10/2020","ha":"14:42:00","vap":54626,"tvap":162824,"pvap":"33,54"},{"dataHoraApuracao":"13/10/2020 14:43:00","da":"13/10/2020","ha":"14:43:00","vap":56355,"tvap":167177,"pvap":"33,7"}]},{"n":14,"nmu":"CANDIDATO 14","c":"#a9a9a9","sgp":"P14","ap":[{"dataHoraApuracao":"09/10/2020 12:51:00","da":"09/10/2020","ha":"12:51:00","vap":348,"tvap":1651,"pvap":"21,07"},{"dataHoraApuracao":"09/10/2020 12:52:00","da":"09/10/2020","ha":"12:52:00","vap":4779,"tvap":14651,"pvap":"32,61"},{"dataHoraApuracao":"09/10/2020 12:53:00","da":"09/10/2020","ha":"12:53:00","vap":7530,"tvap":23386,"pvap":"32,19"},{"dataHoraApuracao":"09/10/2020 13:02:00","da":"09/10/2020","ha":"13:02:00","vap":8473,"tvap":25449,"pvap":"33,29"},{"dataHoraApuracao":"09/10/2020 13:03:00","da":"09/10/2020","ha":"13:03:00","vap":13241,"tvap":39017,"pvap":"33,93"},{"dataHoraApuracao":"09/10/2020 13:04:00","da":"09/10/2020","ha":"13:04:00","vap":15207,"tvap":44593,"pvap":"34,1"},{"dataHoraApuracao":"09/10/2020 13:16:00","da":"09/10/2020","ha":"13:16:00","vap":16164,"tvap":46770,"pvap":"34,56"},{"dataHoraApuracao":"09/10/2020 13:17:00","da":"09/10/2020","ha":"13:17:00","vap":17942,"tvap":53311,"pvap":"33,65"},{"dataHoraApuracao":"09/10/2020 13:18:00","da":"09/10/2020","ha":"13:18:00","vap":17956,"tvap":53386,"pvap":"33,63"},{"dataHoraApuracao":"09/10/2020 13:26:00","da":"09/10/2020","ha":"13:26:00","vap":17965,"tvap":53571,"pvap":"33,53"},{"dataHoraApuracao":"09/10/2020 13:28:00","da":"09/10/2020","ha":"13:28:00","vap":17966,"tvap":53629,"pvap":"33,5"},{"dataHoraApuracao":"09/10/2020 13:29:00","da":"09/10/2020","ha":"13:29:00","vap":17978,"tvap":53672,"pvap":"33,49"},{"dataHoraApuracao":"09/10/2020 13:58:00","da":"09/10/2020","ha":"13:58:00","vap":18139,"tvap":53947,"pvap":"33,62"},{"dataHoraApuracao":"09/10/2020 15:01:00","da":"09/10/2020","ha":"15:01:00","vap":18871,"tvap":56074,"pvap":"33,65"},{"dataHoraApuracao":"09/10/2020 15:02:00","da":"09/10/2020","ha":"15:02:00","vap":19591,"tvap":58246,"pvap":"33,63"},{"dataHoraApuracao":"09/10/2020 15:03:00","da":"09/10/2020","ha":"15:03:00","vap":24341,"tvap":73216,"pvap":"33,24"},{"dataHoraApuracao":"09/10/2020 15:05:00","da":"09/10/2020","ha":"15:05:00","vap":28712,"tvap":86235,"pvap":"33,29"},{"dataHoraApuracao":"09/10/2020 15:06:00","da":"09/10/2020","ha":"15:06:00","vap":30349,"tvap":90407,"pvap":"33,56"},{"dataHoraApuracao":"09/10/2020 15:07:00","da":"09/10/2020","ha":"15:07:00","vap":30396,"tvap":90595,"pvap":"33,55"},{"dataHoraApuracao":"09/10/2020 15:08:00","da":"09/10/2020","ha":"15:08:00","vap":30644,"tvap":90878,"pvap":"33,71"},{"dataHoraApuracao":"09/10/2020 15:09:00","da":"09/10/2020","ha":"15:09:00","vap":32347,"tvap":96799,"pvap":"33,41"},{"dataHoraApuracao":"09/10/2020 15:10:00","da":"09/10/2020","ha":"15:10:00","vap":37765,"tvap":113629,"pvap":"33,23"},{"dataHoraApuracao":"09/10/2020 15:11:00","da":"09/10/2020","ha":"15:11:00","vap":38424,"tvap":116114,"pvap":"33,09"},{"dataHoraApuracao":"09/10/2020 15:27:00","da":"09/10/2020","ha":"15:27:00","vap":38503,"tvap":116263,"pvap":"33,11"},{"dataHoraApuracao":"13/10/2020 14:39:00","da":"13/10/2020","ha":"14:39:00","vap":40428,"tvap":122792,"pvap":"32,92"},{"dataHoraApuracao":"13/10/2020 14:40:00","da":"13/10/2020","ha":"14:40:00","vap":43699,"tvap":132393,"pvap":"33"},{"dataHoraApuracao":"13/10/2020 14:41:00","da":"13/10/2020","ha":"14:41:00","vap":49450,"tvap":147359,"pvap":"33,55"},{"dataHoraApuracao":"13/10/2020 14:42:00","da":"13/10/2020","ha":"14:42:00","vap":53895,"tvap":162824,"pvap":"33,1"},{"dataHoraApuracao":"13/10/2020 14:43:00","da":"13/10/2020","ha":"14:43:00","vap":55628,"tvap":167177,"pvap":"33,27"}]},{"n":23,"nmu":"CANDIDATO 23","c":"#a9a9a9","sgp":"P23","ap":[{"dataHoraApuracao":"09/10/2020 12:51:00","da":"09/10/2020","ha":"12:51:00","vap":893,"tvap":1651,"pvap":"54,08"},{"dataHoraApuracao":"09/10/2020 12:52:00","da":"09/10/2020","ha":"12:52:00","vap":5605,"tvap":14651,"pvap":"38,25"},{"dataHoraApuracao":"09/10/2020 12:53:00","da":"09/10/2020","ha":"12:53:00","vap":9093,"tvap":23386,"pvap":"38,88"},{"dataHoraApuracao":"09/10/2020 13:02:00","da":"09/10/2020","ha":"13:02:00","vap":9499,"tvap":25449,"pvap":"37,32"},{"dataHoraApuracao":"09/10/2020 13:03:00","da":"09/10/2020","ha":"13:03:00","vap":13890,"tvap":39017,"pvap":"35,59"},{"dataHoraApuracao":"09/10/2020 13:04:00","da":"09/10/2020","ha":"13:04:00","vap":15392,"tvap":44593,"pvap":"34,51"},{"dataHoraApuracao":"09/10/2020 13:16:00","da":"09/10/2020","ha":"13:16:00","vap":16043,"tvap":46770,"pvap":"34,3"},{"dataHoraApuracao":"09/10/2020 13:17:00","da":"09/10/2020","ha":"13:17:00","vap":18225,"tvap":53311,"pvap":"34,18"},{"dataHoraApuracao":"09/10/2020 13:18:00","da":"09/10/2020","ha":"13:18:00","vap":18282,"tvap":53386,"pvap":"34,24"},{"dataHoraApuracao":"09/10/2020 13:26:00","da":"09/10/2020","ha":"13:26:00","vap":18456,"tvap":53571,"pvap":"34,45"},{"dataHoraApuracao":"09/10/2020 13:28:00","da":"09/10/2020","ha":"13:28:00","vap":18509,"tvap":53629,"pvap":"34,51"},{"dataHoraApuracao":"09/10/2020 13:29:00","da":"09/10/2020","ha":"13:29:00","vap":18525,"tvap":53672,"pvap":"34,51"},{"dataHoraApuracao":"09/10/2020 13:58:00","da":"09/10/2020","ha":"13:58:00","vap":18532,"tvap":53947,"pvap":"34,35"},{"dataHoraApuracao":"09/10/2020 15:01:00","da":"09/10/2020","ha":"15:01:00","vap":19241,"tvap":56074,"pvap":"34,31"},{"dataHoraApuracao":"09/10/2020 15:02:00","da":"09/10/2020","ha":"15:02:00","vap":20012,"tvap":58246,"pvap":"34,35"},{"dataHoraApuracao":"09/10/2020 15:03:00","da":"09/10/2020","ha":"15:03:00","vap":24791,"tvap":73216,"pvap":"33,86"},{"dataHoraApuracao":"09/10/2020 15:05:00","da":"09/10/2020","ha":"15:05:00","vap":30001,"tvap":86235,"pvap":"34,78"},{"dataHoraApuracao":"09/10/2020 15:06:00","da":"09/10/2020","ha":"15:06:00","vap":31041,"tvap":90407,"pvap":"34,33"},{"dataHoraApuracao":"09/10/2020 15:07:00","da":"09/10/2020","ha":"15:07:00","vap":31081,"tvap":90595,"pvap":"34,3"},{"dataHoraApuracao":"09/10/2020 15:08:00","da":"09/10/2020","ha":"15:08:00","vap":31114,"tvap":90878,"pvap":"34,23"},{"dataHoraApuracao":"09/10/2020 15:09:00","da":"09/10/2020","ha":"15:09:00","vap":33498,"tvap":96799,"pvap":"34,6"},{"dataHoraApuracao":"09/10/2020 15:10:00","da":"09/10/2020","ha":"15:10:00","vap":38352,"tvap":113629,"pvap":"33,75"},{"dataHoraApuracao":"09/10/2020 15:11:00","da":"09/10/2020","ha":"15:11:00","vap":39078,"tvap":116114,"pvap":"33,65"},{"dataHoraApuracao":"09/10/2020 15:27:00","da":"09/10/2020","ha":"15:27:00","vap":39117,"tvap":116263,"pvap":"33,64"},{"dataHoraApuracao":"13/10/2020 14:39:00","da":"13/10/2020","ha":"14:39:00","vap":41061,"tvap":122792,"pvap":"33,43"},{"dataHoraApuracao":"13/10/2020 14:40:00","da":"13/10/2020","ha":"14:40:00","vap":44271,"tvap":132393,"pvap":"33,43"},{"dataHoraApuracao":"13/10/2020 14:41:00","da":"13/10/2020","ha":"14:41:00","vap":48661,"tvap":147359,"pvap":"33,02"},{"dataHoraApuracao":"13/10/2020 14:42:00","da":"13/10/2020","ha":"14:42:00","vap":54303,"tvap":162824,"pvap":"33,35"},{"dataHoraApuracao":"13/10/2020 14:43:00","da":"13/10/2020","ha":"14:43:00","vap":55194,"tvap":167177,"pvap":"33,01"}]}]}}