{"ele":8707,"carper":11,"t":1,"f":"S","esae":"N","mnae":" ","dg":"13/10/2020","hg":"20:08:15","dv":"S","nadf":"pi12718-c0011-e008707-006-f","abr":[{"dt":"12/10/2020","ht":"13:50:00","tf":"N","and":"P","s":18,"st":18,"pst":" 100,00","snt":0,"psnt":"   0,00","si":18,"psi":" 100,00","sni":0,"psni":"   0,00","sa":18,"psa":" 100,00","sna":0,"psna":"   0,00","e":4451,"ea":4451,"pea":" 100,00","ena":0,"pena":"   0,00","esi":4451,"pesi":" 100,00","esni":0,"pesni":"   0,00","c":3792,"pc":"  85,19","a":659,"pa":"  14,81","tv":3792,"vscv":0,"vb":882,"pvb":"  23,26","tvn":745,"ptvn":"  19,65","vn":745,"pvn":" 100,00","vnt":0,"pvnt":"   0,00","vp":0,"pvp":"   0,00","vv":2165,"pvv":" 100,00","van":0,"pvan":"   0,00","vansj":0,"pvansj":"   0,00","vnom":2165,"pvnom":" 100,00","cand":[{"seq":1,"n":14,"e":"N","vap":1188,"pvap":"  31,33","st":""},{"seq":2,"n":12,"e":"N","vap":977,"pvap":"  25,76","st":""}],"tpabr":"MU","cdabr":"12718","colig":[{"n":180000271556,"tvtn":1188,"tvtl":0,"tvan":1188,"tval":0},{"n":180000271554,"tvtn":977,"tvtl":0,"tvan":977,"tval":0}],"part":[{"n":14,"tvtn":1188,"tvtl":0,"tvan":1188,"tval":0},{"n":12,"tvtn":977,"tvtl":0,"tvan":977,"tval":0}]},{"dt":"12/10/2020","ht":"13:50:00","tf":"N","and":"P","s":18,"st":18,"pst":" 100,00","snt":0,"psnt":"0","si":18,"psi":" 100,00","sni":0,"psni":"   0,00","sa":18,"psa":" 100,00","sna":0,"psna":"   0,00","e":4451,"ea":4451,"pea":" 100,00","ena":0,"pena":"   0,00","esi":4451,"pesi":" 100,00","esni":0,"pesni":"   0,00","c":3792,"pc":"  85,19","a":659,"pa":"  14,81","tv":3792,"vscv":0,"vb":882,"pvb":"  23,26","tvn":745,"ptvn":"  19,65","vn":745,"pvn":" 100,00","vp":0,"pvp":"   0,00","vv":2165,"pvv":" 100,00","van":0,"pvan":"   0,00","vansj":0,"pvansj":"   0,00","vnom":2165,"pvnom":" 100,00","cand":[{"seq":2,"n":12,"e":"N","vap":977,"pvap":"  25,76","st":""},{"seq":1,"n":14,"e":"N","vap":1188,"pvap":"  31,33","st":""}],"tpabr":"ZONA","cdabr":"32"}]}