{"ele":8707,"cdabr":"12319","nmabr":"ALAGOINHA DO PIAUÍ","t":1,"f":"S","s":"N","dg":"13/10/2020","hg":"20:04:22","v":"005","br":{"nm":"Brasil","uf":[{"sg":"PI","nm":"PIAUÍ","mun":[{"cd":"12319","nm":"ALAGOINHA DO PIAUÍ","c":"N","s":25,"e":5671,"tzon":1,"zon":[{"cd":"0029","s":25,"e":5671}]}]}]},"carg":{"cd":11,"nmn":"Prefeito","nmm":"Prefeito","nmf":"Prefeita","nv":1,"col":[{"n":180000271722,"nm":"COLIGACAO 180000271722","tp":"P","com":"P14","par":[{"n":14,"sg":" P14 ","nm":"PARTIDO 14","cand":[{"sqcand":180002291589,"n":14,"nm":"CANDIDATO 14","nmu":"CANDIDATO 14","s":"M","dt":"03/08/1970","dvt":"Válido","vs":[{"sqcand":180002291590,"nm":"CANDIDATO 14 1","nmu":"CANDIDATO 14 1","tp":"V","sgp":"P14"}]}]}]},{"n":180000271720,"nm":"COLIGACAO 180000271720","tp":"P","com":"P12","par":[{"n":12,"sg":" P12 ","nm":"PARTIDO 12","cand":[{"sqcand":180002291578,"n":12,"nm":"CANDIDATO 12","nmu":"CANDIDATO 12","s":"M","dt":"03/02/1929","dvt":"Válido","vs":[{"sqcand":180002291579,"nm":"CANDIDATO 12 1","nmu":"CANDIDATO 12 1","tp":"V","sgp":"P12"}]}]}]}]}}