{"dt":"09/10/2020","ht":"14:03:00","tf":"s","s":59,"st":59,"pst":" 100,00","snt":0,"psnt":"   0,00","si":59,"psi":" 100,00","sni":0,"psni":"   0,00","sa":59,"psa":" 100,00","sna":0,"psna":"   0,00","e":15447,"ea":15447,"pea":" 100,00","ena":0,"pena":"   0,00","esi":15447,"pesi":" 100,00","esni":0,"pesni":"   0,00","c":12537,"pc":"  81,16","a":2910,"pa":"  18,84","tv":12537,"vscv":0,"vb":2050,"pvb":"  16,35","tvn":1875,"ptvn":"  14,96","vn":1875,"pvn":" 100,00","vnt":0,"pvnt":"00.00","vp":0,"pvp":"00.00","vv":6366,"pvv":"  50,78","van":0,"pvan":"00.00","vansj":2246,"pvansj":"  17,91","vnom":6366,"pvnom":" 100,00","cand":[{"seq":4,"sqcand":190002306063,"n":15,"nm":"CANDIDATO 15","cc":"P15","nv":"CANDIDATO 15 1","e":"n","vap":2246,"pvap":"  17,91","st":"Não eleito","dvt":"Anulado sub judice"},{"seq":2,"sqcand":190002306061,"n":11,"nm":"CANDIDATO 11","cc":"P11 -  P11 / P12","nv":"CANDIDATO 11 1","e":"n","vap":1938,"pvap":"  15,46","st":"Não eleito","dvt":"Válido"},{"seq":3,"sqcand":190002306077,"n":20,"nm":"CANDIDATO 20","cc":"P20","nv":"CANDIDATO 20 1","e":"n","vap":1842,"pvap":"  14,69","st":"Não eleito","dvt":"Válido"},{"seq":1,"sqcand":190002306091,"n":23,"nm":"CANDIDATO 23","cc":"P23","nv":"CANDIDATO 23 1","e":"s","vap":2586,"pvap":"  20,63","st":"Eleito","dvt":"Válido"}],"ele":8707,"tpabr":"mu","cdabr":"58556","carper":11,"t":1,"f":"s","dv":"s","esae":"n","mnae":"","v":1}