{"ele":8707,"carper":13,"t":1,"f":"S","esae":"N","mnae":" ","dg":"13/10/2020","hg":"20:05:27","dv":"S","nadf":"mg43052-c0013-e008707-006-f","abr":[{"dt":"08/10/2020","ht":"00:00:00","tf":"N","and":"P","s":176,"st":173,"pst":"  98,30","snt":3,"psnt":"   1,70","si":173,"psi":"  98,30","sni":0,"psni":"   0,00","sa":173,"psa":" 100,00","sna":0,"psna":"   0,00","e":53210,"ea":53210,"pea":" 100,00","ena":0,"pena":"   0,00","esi":53210,"pesi":"  98,30","esni":0,"pesni":"   0,00","c":45308,"pc":"  85,15","a":7902,"pa":"  14,85","tv":45308,"vscv":0,"vb":1816,"pvb":"   4,01","tvn":2691,"ptvn":"   5,94","vn":2691,"pvn":" 100,00","vnt":0,"pvnt":"   0,00","vp":0,"pvp":"   0,00","vv":40801,"pvv":" 100,00","vl":4388,"pvl":"  10,75","van":0,"pvan":"   0,00","vansj":0,"pvansj":"   0,00","vnom":36413,"pvnom":"  89,25","cand":[{"seq":17,"n":13008,"e":"N","vap":1367,"pvap":"   3,02","st":""},{"seq":9,"n":13003,"e":"N","vap":2045,"pvap":"   4,51","st":""},{"seq":2,"n":13006,"e":"N","vap":2579,"pvap":"   5,69","st":""},{"seq":3,"n":13005,"e":"N","vap":2574,"pvap":"   5,68","st":""},{"seq":18,"n":13001,"e":"N","vap":1350,"pvap":"   2,98","st":""},{"seq":15,"n":13009,"e":"N","vap":1649,"pvap":"   3,64","st":""},{"seq":8,"n":13004,"e":"N","vap":2086,"pvap":"   4,60","st":""},{"seq":11,"n":13007,"e":"N","vap":1910,"pvap":"   4,22","st":""},{"seq":7,"n":13002,"e":"N","vap":2107,"pvap":"   4,65","st":""},{"seq":14,"n":14002,"e":"N","vap":1732,"pvap":"   3,82","st":""},{"seq":4,"n":14007,"e":"N","vap":2390,"pvap":"   5,28","st":""},{"seq":10,"n":14008,"e":"N","vap":2023,"pvap":"   4,46","st":""},{"seq":6,"n":14004,"e":"N","vap":2243,"pvap":"   4,95","st":""},{"seq":1,"n":14009,"e":"N","vap":2879,"pvap":"   6,35","st":""},{"seq":16,"n":14006,"e":"N","vap":1616,"pvap":"   3,57","st":""},{"seq":12,"n":14005,"e":"N","vap":1790,"pvap":"   3,95","st":""},{"seq":13,"n":14001,"e":"N","vap":1785,"pvap":"   3,94","st":""},{"seq":5,"n":14003,"e":"N","vap":2288,"pvap":"   5,05","st":""}],"tpabr":"MU","cdabr":"43052","colig":[{"n":130000341343,"tvtn":17667,"tvtl":1904,"tvan":17667,"tval":1904,"vag":4},{"n":130000341342,"tvtn":18746,"tvtl":2484,"tvan":18746,"tval":2484,"vag":5}],"part":[{"n":13,"tvtn":17667,"tvtl":1904,"tvan":17667,"tval":1904},{"n":14,"tvtn":18746,"tvtl":2484,"tvan":18746,"tval":2484}]},{"dt":"08/10/2020","ht":"00:00:00","tf":"N","and":"P","s":176,"st":173,"pst":"  98,30","snt":3,"psnt":"3","si":173,"psi":"  98,30","sni":0,"psni":"   0,00","sa":173,"psa":" 100,00","sna":0,"psna":"   0,00","e":53210,"ea":53210,"pea":" 100,00","ena":0,"pena":"   0,00","esi":53210,"pesi":"  98,30","esni":0,"pesni":"   0,00","c":45308,"pc":"  85,15","a":7902,"pa":"  14,85","tv":45308,"vscv":0,"vb":1816,"pvb":"   4,01","tvn":2691,"ptvn":"   5,94","vn":2691,"pvn":" 100,00","vp":0,"pvp":"   0,00","vv":40801,"pvv":" 100,00","vl":4388,"pvl":"  10,75","van":0,"pvan":"   0,00","vansj":0,"pvansj":"   0,00","vnom":36413,"pvnom":"  89,25","cand":[{"seq":14,"n":14002,"e":"N","vap":1732,"pvap":"   3,82","st":""},{"seq":4,"n":14007,"e":"N","vap":2390,"pvap":"   5,28","st":""},{"seq":10,"n":14008,"e":"N","vap":2023,"pvap":"   4,46","st":""},{"seq":6,"n":14004,"e":"N","vap":2243,"pvap":"   4,95","st":""},{"seq":1,"n":14009,"e":"N","vap":2879,"pvap":"   6,35","st":""},{"seq":16,"n":14006,"e":"N","vap":1616,"pvap":"   3,57","st":""},{"seq":12,"n":14005,"e":"N","vap":1790,"pvap":"   3,95","st":""},{"seq":13,"n":14001,"e":"N","vap":1785,"pvap":"   3,94","st":""},{"seq":5,"n":14003,"e":"N","vap":2288,"pvap":"   5,05","st":""},{"seq":17,"n":13008,"e":"N","vap":1367,"pvap":"   3,02","st":""},{"seq":9,"n":13003,"e":"N","vap":2045,"pvap":"   4,51","st":""},{"seq":2,"n":13006,"e":"N","vap":2579,"pvap":"   5,69","st":""},{"seq":3,"n":13005,"e":"N","vap":2574,"pvap":"   5,68","st":""},{"seq":18,"n":13001,"e":"N","vap":1350,"pvap":"   2,98","st":""},{"seq":15,"n":13009,"e":"N","vap":1649,"pvap":"   3,64","st":""},{"seq":8,"n":13004,"e":"N","vap":2086,"pvap":"   4,60","st":""},{"seq":11,"n":13007,"e":"N","vap":1910,"pvap":"   4,22","st":""},{"seq":7,"n":13002,"e":"N","vap":2107,"pvap":"   4,65","st":""}],"tpabr":"ZONA","cdabr":"79"}]}