{"ele":8707,"carper":11,"t":1,"f":"S","esae":"N","mnae":" ","dg":"13/10/2020","hg":"20:05:12","dv":"S","nadf":"mg52191-c0011-e008707-006-f","abr":[{"dt":"09/10/2020","ht":"17:00:08","tf":"N","and":"P","s":48,"st":48,"pst":" 100,00","snt":0,"psnt":"   0,00","si":48,"psi":" 100,00","sni":0,"psni":"   0,00","sa":48,"psa":" 100,00","sna":0,"psna":"   0,00","e":13958,"ea":13958,"pea":" 100,00","ena":0,"pena":"   0,00","esi":13958,"pesi":" 100,00","esni":0,"pesni":"   0,00","c":10903,"pc":"  78,11","a":3055,"pa":"  21,89","tv":10903,"vscv":0,"vb":2648,"pvb":"  24,29","tvn":2799,"ptvn":"  25,67","vn":2799,"pvn":" 100,00","vnt":0,"pvnt":"   0,00","vp":0,"pvp":"   0,00","vv":5456,"pvv":" 100,00","van":0,"pvan":"   0,00","vansj":0,"pvansj":"   0,00","vnom":5456,"pvnom":" 100,00","cand":[{"seq":2,"n":13,"e":"N","vap":2415,"pvap":"  22,15","st":""},{"seq":1,"n":71,"e":"N","vap":3041,"pvap":"  27,89","st":""}],"tpabr":"MU","cdabr":"52191","colig":[{"n":130000334043,"tvtn":2415,"tvtl":0,"tvan":2415,"tval":0},{"n":130000334037,"tvtn":3041,"tvtl":0,"tvan":3041,"tval":0}],"part":[{"n":13,"tvtn":2415,"tvtl":0,"tvan":2415,"tval":0},{"n":71,"tvtn":3041,"tvtl":0,"tvan":3041,"tval":0}]},{"dt":"09/10/2020","ht":"17:00:08","tf":"N","and":"P","s":48,"st":48,"pst":" 100,00","snt":0,"psnt":"0","si":48,"psi":" 100,00","sni":0,"psni":"   0,00","sa":48,"psa":" 100,00","sna":0,"psna":"   0,00","e":13958,"ea":13958,"pea":" 100,00","ena":0,"pena":"   0,00","esi":13958,"pesi":" 100,00","esni":0,"pesni":"   0,00","c":10903,"pc":"  78,11","a":3055,"pa":"  21,89","tv":10903,"vscv":0,"vb":2648,"pvb":"  24,29","tvn":2799,"ptvn":"  25,67","vn":2799,"pvn":" 100,00","vp":0,"pvp":"   0,00","vv":5456,"pvv":" 100,00","van":0,"pvan":"   0,00","vansj":0,"pvansj":"   0,00","vnom":5456,"pvnom":" 100,00","cand":[{"seq":2,"n":13,"e":"N","vap":2415,"pvap":"  22,15","st":""},{"seq":1,"n":71,"e":"N","vap":3041,"pvap":"  27,89","st":""}],"tpabr":"ZONA","cdabr":"251"}]}