{"ele":8707,"cdabr":"53856","nmabr":"TRÊS CORAÇÕES","t":1,"f":"S","s":"N","dg":"13/10/2020","hg":"20:03:08","v":"005","br":{"nm":"Brasil","uf":[{"sg":"MG","nm":"MINAS GERAIS","mun":[{"cd":"53856","nm":"TRÊS CORAÇÕES","c":"N","s":167,"e":56051,"tzon":1,"zon":[{"cd":"0272","s":167,"e":56051}]}]}]},"carg":{"cd":13,"nmn":"Vereador","nmm":"Vereador","nmf":"Vereadora","nv":9,"col":[{"n":130000320105,"nm":"COLIGACAO 130000320105","tp":"P","com":"P71","par":[{"n":71,"sg":" P71 ","nm":"PARTIDO 71","cand":[{"sqcand":130002454879,"n":71004,"nm":"CANDIDATO 71004","nmu":"CANDIDATO 71004","s":"M","dt":"31/12/1926","dvt":"Válido"},{"sqcand":130002454882,"n":71007,"nm":"CANDIDATO 71007","nmu":"CANDIDATO 71007","s":"M","dt":"02/10/1929","dvt":"Válido"},{"sqcand":130002454883,"n":71008,"nm":"CANDIDATO 71008","nmu":"CANDIDATO 71008","s":"M","dt":"20/06/1929","dvt":"Válido"},{"sqcand":130002454877,"n":71002,"nm":"CANDIDATO 71002","nmu":"CANDIDATO 71002","s":"F","dt":"12/01/1926","dvt":"Válido"},{"sqcand":130002454884,"n":71009,"nm":"CANDIDATO 71009","nmu":"CANDIDATO 71009","s":"M","dt":"27/08/1977","dvt":"Válido"},{"sqcand":130002454876,"n":71001,"nm":"CANDIDATO 71001","nmu":"CANDIDATO 71001","s":"F","dt":"06/11/1929","dvt":"Válido"},{"sqcand":130002454881,"n":71006,"nm":"CANDIDATO 71006","nmu":"CANDIDATO 71006","s":"M","dt":"25/12/1928","dvt":"Válido"},{"sqcand":130002454880,"n":71005,"nm":"CANDIDATO 71005","nmu":"CANDIDATO 71005","s":"M","dt":"17/05/1972","dvt":"Válido"},{"sqcand":130002454878,"n":71003,"nm":"CANDIDATO 71003","nmu":"CANDIDATO 71003","s":"M","dt":"31/12/1920","dvt":"Válido"}]}]},{"n":130000320108,"nm":"COLIGACAO 130000320108","tp":"P","com":"P24","par":[{"n":24,"sg":" P24 ","nm":"PARTIDO 24","cand":[{"sqcand":130002454903,"n":24001,"nm":"CANDIDATO 24001","nmu":"CANDIDATO 24001","s":"F","dt":"25/07/1929","dvt":"Válido"},{"sqcand":130002454908,"n":24006,"nm":"CANDIDATO 24006","nmu":"CANDIDATO 24006","s":"M","dt":"08/05/1925","dvt":"Válido"},{"sqcand":130002454909,"n":24007,"nm":"CANDIDATO 24007","nmu":"CANDIDATO 24007","s":"M","dt":"16/04/1929","dvt":"Válido"},{"sqcand":130002454904,"n":24002,"nm":"CANDIDATO 24002","nmu":"CANDIDATO 24002","s":"F","dt":"24/07/1928","dvt":"Válido"},{"sqcand":130002454905,"n":24003,"nm":"CANDIDATO 24003","nmu":"CANDIDATO 24003","s":"M","dt":"07/08/1981","dvt":"Válido"},{"sqcand":130002454907,"n":24005,"nm":"CANDIDATO 24005","nmu":"CANDIDATO 24005","s":"M","dt":"30/10/1929","dvt":"Válido"},{"sqcand":130002454906,"n":24004,"nm":"CANDIDATO 24004","nmu":"CANDIDATO 24004","s":"M","dt":"10/08/1928","dvt":"Válido"},{"sqcand":130002454911,"n":24009,"nm":"CANDIDATO 24009","nmu":"CANDIDATO 24009","s":"M","dt":"03/12/1926","dvt":"Válido"},{"sqcand":130002454910,"n":24008,"nm":"CANDIDATO 24008","nmu":"CANDIDATO 24008","s":"M","dt":"30/12/1924","dvt":"Válido"}]}]}]}}