{"ele":8707,"carper":13,"t":1,"f":"S","esae":"N","mnae":" ","dg":"13/10/2020","hg":"20:05:08","dv":"S","nadf":"mg54038-c0013-e008707-006-f","abr":[{"dt":"08/10/2020","ht":"00:00:00","tf":"N","and":"P","s":1658,"st":1418,"pst":"  85,52","snt":240,"psnt":"  14,48","si":1418,"psi":"  85,52","sni":0,"psni":"   0,00","sa":1418,"psa":" 100,00","sna":0,"psna":"   0,00","e":399366,"ea":399366,"pea":" 100,00","ena":0,"pena":"   0,00","esi":399366,"pesi":"  85,52","esni":0,"pesni":"   0,00","c":338388,"pc":"  84,73","a":60978,"pa":"  15,27","tv":338388,"vscv":0,"vb":13863,"pvb":"   4,10","tvn":14059,"ptvn":"   4,15","vn":14059,"pvn":" 100,00","vnt":0,"pvnt":"   0,00","vp":0,"pvp":"   0,00","vv":310466,"pvv":" 100,00","vl":34047,"pvl":"  10,97","van":0,"pvan":"   0,00","vansj":0,"pvansj":"   0,00","vnom":276419,"pvnom":"  89,03","cand":[{"seq":12,"n":16004,"e":"N","vap":15389,"pvap":"   4,55","st":""},{"seq":16,"n":16009,"e":"N","vap":13994,"pvap":"   4,14","st":""},{"seq":17,"n":16007,"e":"N","vap":13555,"pvap":"   4,01","st":""},{"seq":18,"n":16001,"e":"N","vap":13077,"pvap":"   3,86","st":""},{"seq":3,"n":16008,"e":"N","vap":16350,"pvap":"   4,83","st":""},{"seq":11,"n":16005,"e":"N","vap":15477,"pvap":"   4,57","st":""},{"seq":9,"n":16002,"e":"N","vap":15530,"pvap":"   4,59","st":""},{"seq":4,"n":16003,"e":"N","vap":16040,"pvap":"   4,74","st":""},{"seq":1,"n":16006,"e":"N","vap":17898,"pvap":"   5,29","st":""},{"seq":13,"n":24009,"e":"N","vap":15084,"pvap":"   4,46","st":""},{"seq":5,"n":24008,"e":"N","vap":15860,"pvap":"   4,69","st":""},{"seq":15,"n":24007,"e":"N","vap":14208,"pvap":"   4,20","st":""},{"seq":14,"n":24004,"e":"N","vap":14424,"pvap":"   4,26","st":""},{"seq":8,"n":24001,"e":"N","vap":15565,"pvap":"   4,60","st":""},{"seq":7,"n":24006,"e":"N","vap":15739,"pvap":"   4,65","st":""},{"seq":10,"n":24003,"e":"N","vap":15491,"pvap":"   4,58","st":""},{"seq":2,"n":24002,"e":"N","vap":16906,"pvap":"   5,00","st":""},{"seq":6,"n":24005,"e":"N","vap":15832,"pvap":"   4,68","st":""}],"tpabr":"MU","cdabr":"54038","colig":[{"n":130000315750,"tvtn":137310,"tvtl":71064,"tvan":137310,"tval":71064,"vag":4},{"n":130000315709,"tvtn":139109,"tvtl":65124,"tvan":139109,"tval":65124,"vag":5}],"part":[{"n":16,"tvtn":137310,"tvtl":71064,"tvan":137310,"tval":71064},{"n":24,"tvtn":139109,"tvtl":65124,"tvan":139109,"tval":65124}]},{"dt":"08/10/2020","ht":"00:00:00","tf":"N","and":"P","s":417,"st":417,"pst":" 100,00","snt":0,"psnt":"0","si":417,"psi":" 100,00","sni":0,"psni":"   0,00","sa":417,"psa":" 100,00","sna":0,"psna":"   0,00","e":116621,"ea":116621,"pea":" 100,00","ena":0,"pena":"   0,00","esi":116621,"pesi":" 100,00","esni":0,"pesni":"   0,00","c":98717,"pc":"  84,65","a":17904,"pa":"  15,35","tv":98717,"vscv":0,"vb":3845,"pvb":"   3,90","tvn":4502,"ptvn":"   4,56","vn":4502,"pvn":" 100,00","vp":0,"pvp":"   0,00","vv":90370,"pvv":" 100,00","vl":10363,"pvl":"  11,47","van":0,"pvan":"   0,00","vansj":0,"pvansj":"   0,00","vnom":80007,"pvnom":"  88,53","cand":[{"seq":12,"n":16004,"e":"N","vap":4807,"pvap":"   4,87","st":""},{"seq":16,"n":16009,"e":"N","vap":3918,"pvap":"   3,97","st":""},{"seq":17,"n":16007,"e":"N","vap":4451,"pvap":"   4,51","st":""},{"seq":3,"n":16008,"e":"N","vap":4555,"pvap":"   4,61","st":""},{"seq":18,"n":16001,"e":"N","vap":3030,"pvap":"   3,07","st":""},{"seq":11,"n":16005,"e":"N","vap":4375,"pvap":"   4,43","st":""},{"seq":9,"n":16002,"e":"N","vap":5215,"pvap":"   5,28","st":""},{"seq":4,"n":16003,"e":"N","vap":4585,"pvap":"   4,64","st":""},{"seq":1,"n":16006,"e":"N","vap":4535,"pvap":"   4,59","st":""},{"seq":13,"n":24009,"e":"N","vap":4534,"pvap":"   4,59","st":""},{"seq":5,"n":24008,"e":"N","vap":4757,"pvap":"   4,82","st":""},{"seq":15,"n":24007,"e":"N","vap":3875,"pvap":"   3,93","st":""},{"seq":14,"n":24004,"e":"N","vap":4184,"pvap":"   4,24","st":""},{"seq":8,"n":24001,"e":"N","vap":4297,"pvap":"   4,35","st":""},{"seq":7,"n":24006,"e":"N","vap":4381,"pvap":"   4,44","st":""},{"seq":10,"n":24003,"e":"N","vap":5161,"pvap":"   5,23","st":""},{"seq":2,"n":24002,"e":"N","vap":4877,"pvap":"   4,94","st":""},{"seq":6,"n":24005,"e":"N","vap":4470,"pvap":"   4,53","st":""}],"tpabr":"ZONA","cdabr":"278"},{"dt":"08/10/2020","ht":"00:00:00","tf":"N","and":"P","s":417,"st":416,"pst":"  99,76","snt":1,"psnt":"1","si":416,"psi":"  99,76","sni":0,"psni":"   0,00","sa":416,"psa":" 100,00","sna":0,"psna":"   0,00","e":121196,"ea":121196,"pea":" 100,00","ena":0,"pena":"   0,00","esi":121196,"pesi":"  99,76","esni":0,"pesni":"   0,00","c":103008,"pc":"  84,99","a":18188,"pa":"  15,01","tv":103008,"vscv":0,"vb":4271,"pvb":"   4,15","tvn":4181,"ptvn":"   4,06","vn":4181,"pvn":" 100,00","vp":0,"pvp":"   0,00","vv":94556,"pvv":" 100,00","vl":10170,"pvl":"  10,76","van":0,"pvan":"   0,00","vansj":0,"pvansj":"   0,00","vnom":84386,"pvnom":"  89,24","cand":[{"seq":12,"n":16004,"e":"N","vap":4786,"pvap":"   4,65","st":""},{"seq":16,"n":16009,"e":"N","vap":4047,"pvap":"   3,93","st":""},{"seq":17,"n":16007,"e":"N","vap":3652,"pvap":"   3,55","st":""},{"seq":18,"n":16001,"e":"N","vap":4309,"pvap":"   4,18","st":""},{"seq":3,"n":16008,"e":"N","vap":4707,"pvap":"   4,57","st":""},{"seq":9,"n":16002,"e":"N","vap":5333,"pvap":"   5,18","st":""},{"seq":11,"n":16005,"e":"N","vap":5326,"pvap":"   5,17","st":""},{"seq":4,"n":16003,"e":"N","vap":5053,"pvap":"   4,91","st":""},{"seq":1,"n":16006,"e":"N","vap":5439,"pvap":"   5,28","st":""},{"seq":13,"n":24009,"e":"N","vap":4316,"pvap":"   4,19","st":""},{"seq":5,"n":24008,"e":"N","vap":4514,"pvap":"   4,38","st":""},{"seq":14,"n":24004,"e":"N","vap":4267,"pvap":"   4,14","st":""},{"seq":15,"n":24007,"e":"N","vap":3264,"pvap":"   3,17","st":""},{"seq":7,"n":24006,"e":"N","vap":5167,"pvap":"   5,02","st":""},{"seq":8,"n":24001,"e":"N","vap":4709,"pvap":"   4,57","st":""},{"seq":10,"n":24003,"e":"N","vap":4272,"pvap":"   4,15","st":""},{"seq":2,"n":24002,"e":"N","vap":5597,"pvap":"   5,43","st":""},{"seq":6,"n":24005,"e":"N","vap":5628,"pvap":"   5,46","st":""}],"tpabr":"ZONA","cdabr":"279"},{"dt":"08/10/2020","ht":"00:00:00","tf":"N","and":"P","s":299,"st":299,"pst":" 100,00","snt":0,"psnt":"0","si":299,"psi":" 100,00","sni":0,"psni":"   0,00","sa":299,"psa":" 100,00","sna":0,"psna":"   0,00","e":87940,"ea":87940,"pea":" 100,00","ena":0,"pena":"   0,00","esi":87940,"pesi":" 100,00","esni":0,"pesni":"   0,00","c":74279,"pc":"  84,47","a":13661,"pa":"  15,53","tv":74279,"vscv":0,"vb":3078,"pvb":"   4,14","tvn":3321,"ptvn":"   4,47","vn":3321,"pvn":" 100,00","vp":0,"pvp":"   0,00","vv":67880,"pvv":" 100,00","vl":7120,"pvl":"  10,49","van":0,"pvan":"   0,00","vansj":0,"pvansj":"   0,00","vnom":60760,"pvnom":"  89,51","cand":[{"seq":13,"n":24009,"e":"N","vap":3492,"pvap":"   4,70","st":""},{"seq":5,"n":24008,"e":"N","vap":3799,"pvap":"   5,11","st":""},{"seq":15,"n":24007,"e":"N","vap":2914,"pvap":"   3,92","st":""},{"seq":14,"n":24004,"e":"N","vap":3537,"pvap":"   4,76","st":""},{"seq":8,"n":24001,"e":"N","vap":3936,"pvap":"   5,30","st":""},{"seq":7,"n":24006,"e":"N","vap":3032,"pvap":"   4,08","st":""},{"seq":10,"n":24003,"e":"N","vap":4267,"pvap":"   5,74","st":""},{"seq":2,"n":24002,"e":"N","vap":2893,"pvap":"   3,89","st":""},{"seq":6,"n":24005,"e":"N","vap":3522,"pvap":"   4,74","st":""},{"seq":12,"n":16004,"e":"N","vap":2665,"pvap":"   3,59","st":""},{"seq":17,"n":16007,"e":"N","vap":2755,"pvap":"   3,71","st":""},{"seq":16,"n":16009,"e":"N","vap":3093,"pvap":"   4,16","st":""},{"seq":3,"n":16008,"e":"N","vap":3493,"pvap":"   4,70","st":""},{"seq":18,"n":16001,"e":"N","vap":3401,"pvap":"   4,58","st":""},{"seq":11,"n":16005,"e":"N","vap":3561,"pvap":"   4,79","st":""},{"seq":9,"n":16002,"e":"N","vap":2457,"pvap":"   3,31","st":""},{"seq":4,"n":16003,"e":"N","vap":3399,"pvap":"   4,58","st":""},{"seq":1,"n":16006,"e":"N","vap":4544,"pvap":"   6,12","st":""}],"tpabr":"ZONA","cdabr":"314"},{"dt":"08/10/2020","ht":"00:00:00","tf":"N","and":"P","s":242,"st":3,"pst":"   1,24","snt":239,"psnt":"239","si":3,"psi":"   1,24","sni":0,"psni":"   0,00","sa":3,"psa":" 100,00","sna":0,"psna":"   0,00","e":406,"ea":406,"pea":" 100,00","ena":0,"pena":"   0,00","esi":406,"pesi":"   1,24","esni":0,"pesni":"   0,00","c":31,"pc":"   7,64","a":375,"pa":"  92,36","tv":31,"vscv":0,"vb":0,"pvb":"   0,00","tvn":0,"ptvn":"   0,00","vn":0,"pvn":"   0,00","vp":0,"pvp":"   0,00","vv":31,"pvv":" 100,00","vl":0,"pvl":"   0,00","van":0,"pvan":"   0,00","vansj":0,"pvansj":"   0,00","vnom":31,"pvnom":" 100,00","cand":[{"seq":14,"n":24004,"e":"N","vap":1,"pvap":"   3,23","st":""},{"seq":8,"n":24001,"e":"N","vap":5,"pvap":"  16,13","st":""},{"seq":10,"n":24003,"e":"N","vap":6,"pvap":"  19,35","st":""},{"seq":2,"n":24002,"e":"N","vap":6,"pvap":"  19,35","st":""},{"seq":12,"n":16004,"e":"N","vap":2,"pvap":"   6,45","st":""},{"seq":18,"n":16001,"e":"N","vap":3,"pvap":"   9,68","st":""},{"seq":3,"n":16008,"e":"N","vap":1,"pvap":"   3,23","st":""},{"seq":9,"n":16002,"e":"N","vap":2,"pvap":"   6,45","st":""},{"seq":11,"n":16005,"e":"N","vap":2,"pvap":"   6,45","st":""},{"seq":1,"n":16006,"e":"N","vap":1,"pvap":"   3,23","st":""},{"seq":4,"n":16003,"e":"N","vap":2,"pvap":"   6,45","st":""}],"tpabr":"ZONA","cdabr":"335"},{"dt":"08/10/2020","ht":"00:00:00","tf":"N","and":"P","s":283,"st":283,"pst":" 100,00","snt":0,"psnt":"0","si":283,"psi":" 100,00","sni":0,"psni":"   0,00","sa":283,"psa":" 100,00","sna":0,"psna":"   0,00","e":73203,"ea":73203,"pea":" 100,00","ena":0,"pena":"   0,00","esi":73203,"pesi":" 100,00","esni":0,"pesni":"   0,00","c":62353,"pc":"  85,18","a":10850,"pa":"  14,82","tv":62353,"vscv":0,"vb":2669,"pvb":"   4,28","tvn":2055,"ptvn":"   3,30","vn":2055,"pvn":" 100,00","vp":0,"pvp":"   0,00","vv":57629,"pvv":" 100,00","vl":6394,"pvl":"  11,10","van":0,"pvan":"   0,00","vansj":0,"pvansj":"   0,00","vnom":51235,"pvnom":"  88,90","cand":[{"seq":12,"n":16004,"e":"N","vap":3129,"pvap":"   5,02","st":""},{"seq":16,"n":16009,"e":"N","vap":2936,"pvap":"   4,71","st":""},{"seq":17,"n":16007,"e":"N","vap":2697,"pvap":"   4,33","st":""},{"seq":18,"n":16001,"e":"N","vap":2334,"pvap":"   3,74","st":""},{"seq":3,"n":16008,"e":"N","vap":3594,"pvap":"   5,76","st":""},{"seq":9,"n":16002,"e":"N","vap":2523,"pvap":"   4,05","st":""},{"seq":11,"n":16005,"e":"N","vap":2213,"pvap":"   3,55","st":""},{"seq":4,"n":16003,"e":"N","vap":3001,"pvap":"   4,81","st":""},{"seq":1,"n":16006,"e":"N","vap":3379,"pvap":"   5,42","st":""},{"seq":13,"n":24009,"e":"N","vap":2742,"pvap":"   4,40","st":""},{"seq":5,"n":24008,"e":"N","vap":2790,"pvap":"   4,47","st":""},{"seq":14,"n":24004,"e":"N","vap":2435,"pvap":"   3,91","st":""},{"seq":15,"n":24007,"e":"N","vap":4155,"pvap":"   6,66","st":""},{"seq":8,"n":24001,"e":"N","vap":2618,"pvap":"   4,20","st":""},{"seq":7,"n":24006,"e":"N","vap":3159,"pvap":"   5,07","st":""},{"seq":10,"n":24003,"e":"N","vap":1785,"pvap":"   2,86","st":""},{"seq":2,"n":24002,"e":"N","vap":3533,"pvap":"   5,67","st":""},{"seq":6,"n":24005,"e":"N","vap":2212,"pvap":"   3,55","st":""}],"tpabr":"ZONA","cdabr":"299"}]}