{"ele":8707,"carper":11,"t":1,"f":"S","esae":"N","mnae":" ","dg":"13/10/2020","hg":"20:03:33","dv":"S","nadf":"rn16373-c0011-e008707-006-f","abr":[{"dt":"08/10/2020","ht":"18:54:02","tf":"S","and":"F","s":11,"st":11,"pst":" 100,00","snt":0,"psnt":"   0,00","si":11,"psi":" 100,00","sni":0,"psni":"   0,00","sa":11,"psa":" 100,00","sna":0,"psna":"   0,00","e":3331,"ea":3331,"pea":" 100,00","ena":0,"pena":"   0,00","esi":3331,"pesi":" 100,00","esni":0,"pesni":"   0,00","c":1709,"pc":"  51,31","a":1622,"pa":"  48,69","tv":1709,"vscv":0,"vb":608,"pvb":"  35,58","tvn":270,"ptvn":"  15,80","vn":270,"pvn":" 100,00","vnt":0,"pvnt":"   0,00","vp":0,"pvp":"   0,00","vv":831,"pvv":" 100,00","van":0,"pvan":"   0,00","vansj":0,"pvansj":"   0,00","vnom":831,"pvnom":" 100,00","cand":[{"seq":2,"n":20,"e":"N","vap":231,"pvap":"  13,52","st":"N達o eleito"},{"seq":3,"n":12,"e":"N","vap":162,"pvap":"   9,48","st":"N達o eleito"},{"seq":1,"n":46,"e":"S","vap":438,"pvap":"  25,63","st":"Eleito"}],"tpabr":"MU","cdabr":"16373","colig":[{"n":200000280536,"tvtn":231,"tvtl":0,"tvan":231,"tval":0},{"n":200000280537,"tvtn":162,"tvtl":0,"tvan":162,"tval":0},{"n":200000280538,"tvtn":438,"tvtl":0,"tvan":438,"tval":0}],"part":[{"n":20,"tvtn":231,"tvtl":0,"tvan":231,"tval":0},{"n":12,"tvtn":162,"tvtl":0,"tvan":162,"tval":0},{"n":46,"tvtn":438,"tvtl":0,"tvan":438,"tval":0}]},{"dt":"08/10/2020","ht":"18:54:02","tf":"S","and":"F","s":11,"st":11,"pst":" 100,00","snt":0,"psnt":"0","si":11,"psi":" 100,00","sni":0,"psni":"   0,00","sa":11,"psa":" 100,00","sna":0,"psna":"   0,00","e":3331,"ea":3331,"pea":" 100,00","ena":0,"pena":"   0,00","esi":3331,"pesi":" 100,00","esni":0,"pesni":"   0,00","c":1709,"pc":"  51,31","a":1622,"pa":"  48,69","tv":1709,"vscv":0,"vb":608,"pvb":"  35,58","tvn":270,"ptvn":"  15,80","vn":270,"pvn":" 100,00","vp":0,"pvp":"   0,00","vv":831,"pvv":" 100,00","van":0,"pvan":"   0,00","vansj":0,"pvansj":"   0,00","vnom":831,"pvnom":" 100,00","cand":[{"seq":2,"n":20,"e":"N","vap":231,"pvap":"  13,52","st":"N達o eleito"},{"seq":1,"n":46,"e":"S","vap":438,"pvap":"  25,63","st":"Eleito"},{"seq":3,"n":12,"e":"N","vap":162,"pvap":"   9,48","st":"N達o eleito"}],"tpabr":"ZONA","cdabr":"17"}]}