{"dt":"13/10/2020","ht":"16:55:03","tf":"n","s":562,"st":311,"pst":"  55,34","snt":251,"psnt":"  44,66","si":311,"psi":"  55,34","sni":0,"psni":"   0,00","sa":311,"psa":" 100,00","sna":0,"psna":"   0,00","e":99228,"ea":99228,"pea":" 100,00","ena":0,"pena":"   0,00","esi":99228,"pesi":"  55,34","esni":0,"pesni":"   0,00","c":83586,"pc":"  84,24","a":15642,"pa":"  15,76","tv":83586,"vscv":0,"vb":2202,"pvb":"   2,64","tvn":3254,"ptvn":"   3,89","vn":3254,"pvn":" 100,00","vnt":0,"pvnt":"00.00","vp":0,"pvp":"00.00","vv":78130,"pvv":"  93,47","vl":5134,"pvl":"   6,57","van":0,"pvan":"00.00","vansj":0,"pvansj":"00.00","vnom":72996,"pvnom":"  93,43","cand":[{"seq":26,"sqcand":160002462627,"n":16010,"nm":"CANDIDATO 16010","cc":"P16","nv":" ","e":"n","vap":1902,"pvap":"   2,28","st":"","dvt":"Válido"},{"seq":23,"sqcand":160002462595,"n":14013,"nm":"CANDIDATO 14013","cc":"P14","nv":" ","e":"n","vap":2069,"pvap":"   2,48","st":"","dvt":"Válido"},{"seq":2,"sqcand":160002462596,"n":14014,"nm":"CANDIDATO 14014","cc":"P14","nv":" ","e":"n","vap":3149,"pvap":"   3,77","st":"","dvt":"Válido"},{"seq":7,"sqcand":160002462623,"n":16006,"nm":"CANDIDATO 16006","cc":"P16","nv":" ","e":"n","vap":2899,"pvap":"   3,47","st":"","dvt":"Válido"},{"seq":25,"sqcand":160002462622,"n":16005,"nm":"CANDIDATO 16005","cc":"P16","nv":" ","e":"n","vap":1980,"pvap":"   2,37","st":"","dvt":"Válido"},{"seq":14,"sqcand":160002462593,"n":14011,"nm":"CANDIDATO 14011","cc":"P14","nv":" ","e":"n","vap":2462,"pvap":"   2,95","st":"","dvt":"Válido"},{"seq":22,"sqcand":160002462588,"n":14006,"nm":"CANDIDATO 14006","cc":"P14","nv":" ","e":"n","vap":2135,"pvap":"   2,55","st":"","dvt":"Válido"},{"seq":29,"sqcand":160002462586,"n":14004,"nm":"CANDIDATO 14004","cc":"P14","nv":" ","e":"n","vap":1699,"pvap":"   2,03","st":"","dvt":"Válido"},{"seq":24,"sqcand":160002462597,"n":14015,"nm":"CANDIDATO 14015","cc":"P14","nv":" ","e":"n","vap":2054,"pvap":"   2,46","st":"","dvt":"Válido"},{"seq":3,"sqcand":160002462592,"n":14010,"nm":"CANDIDATO 14010","cc":"P14","nv":" ","e":"n","vap":3093,"pvap":"   3,70","st":"","dvt":"Válido"},{"seq":12,"sqcand":160002462631,"n":16014,"nm":"CANDIDATO 16014","cc":"P16","nv":" ","e":"n","vap":2574,"pvap":"   3,08","st":"","dvt":"Válido"},{"seq":11,"sqcand":160002462620,"n":16003,"nm":"CANDIDATO 16003","cc":"P16","nv":" ","e":"n","vap":2712,"pvap":"   3,24","st":"","dvt":"Válido"},{"seq":19,"sqcand":160002462587,"n":14005,"nm":"CANDIDATO 14005","cc":"P14","nv":" ","e":"n","vap":2344,"pvap":"   2,80","st":"","dvt":"Válido"},{"seq":20,"sqcand":160002462629,"n":16012,"nm":"CANDIDATO 16012","cc":"P16","nv":" ","e":"n","vap":2177,"pvap":"   2,60","st":"","dvt":"Válido"},{"seq":4,"sqcand":160002462621,"n":16004,"nm":"CANDIDATO 16004","cc":"P16","nv":" ","e":"n","vap":3015,"pvap":"   3,61","st":"","dvt":"Válido"},{"seq":21,"sqcand":160002462628,"n":16011,"nm":"CANDIDATO 16011","cc":"P16","nv":" ","e":"n","vap":2174,"pvap":"   2,60","st":"","dvt":"Válido"},{"seq":18,"sqcand":160002462584,"n":14002,"nm":"CANDIDATO 14002","cc":"P14","nv":" ","e":"n","vap":2358,"pvap":"   2,82","st":"","dvt":"Válido"},{"seq":27,"sqcand":160002462632,"n":16015,"nm":"CANDIDATO 16015","cc":"P16","nv":" ","e":"n","vap":1840,"pvap":"   2,20","st":"","dvt":"Válido"},{"seq":30,"sqcand":160002462619,"n":16002,"nm":"CANDIDATO 16002","cc":"P16","nv":" ","e":"n","vap":1514,"pvap":"   1,81","st":"","dvt":"Válido"},{"seq":10,"sqcand":160002462585,"n":14003,"nm":"CANDIDATO 14003","cc":"P14","nv":" ","e":"n","vap":2746,"pvap":"   3,29","st":"","dvt":"Válido"},{"seq":13,"sqcand":160002462590,"n":14008,"nm":"CANDIDATO 14008","cc":"P14","nv":" ","e":"n","vap":2474,"pvap":"   2,96","st":"","dvt":"Válido"},{"seq":28,"sqcand":160002462618,"n":16001,"nm":"CANDIDATO 16001","cc":"P16","nv":" ","e":"n","vap":1727,"pvap":"   2,07","st":"","dvt":"Válido"},{"seq":15,"sqcand":160002462624,"n":16007,"nm":"CANDIDATO 16007","cc":"P16","nv":" ","e":"n","vap":2453,"pvap":"   2,93","st":"","dvt":"Válido"},{"seq":17,"sqcand":160002462589,"n":14007,"nm":"CANDIDATO 14007","cc":"P14","nv":" ","e":"n","vap":2374,"pvap":"   2,84","st":"","dvt":"Válido"},{"seq":5,"sqcand":160002462626,"n":16009,"nm":"CANDIDATO 16009","cc":"P16","nv":" ","e":"n","vap":2988,"pvap":"   3,57","st":"","dvt":"Válido"},{"seq":16,"sqcand":160002462583,"n":14001,"nm":"CANDIDATO 14001","cc":"P14","nv":" ","e":"n","vap":2404,"pvap":"   2,88","st":"","dvt":"Válido"},{"seq":6,"sqcand":160002462591,"n":14009,"nm":"CANDIDATO 14009","cc":"P14","nv":" ","e":"n","vap":2908,"pvap":"   3,48","st":"","dvt":"Válido"},{"seq":1,"sqcand":160002462594,"n":14012,"nm":"CANDIDATO 14012","cc":"P14","nv":" ","e":"n","vap":3230,"pvap":"   3,86","st":"","dvt":"Válido"},{"seq":9,"sqcand":160002462625,"n":16008,"nm":"CANDIDATO 16008","cc":"P16","nv":" ","e":"n","vap":2759,"pvap":"   3,30","st":"","dvt":"Válido"},{"seq":8,"sqcand":160002462630,"n":16013,"nm":"CANDIDATO 16013","cc":"P16","nv":" ","e":"n","vap":2783,"pvap":"   3,33","st":"","dvt":"Válido"}],"ele":8707,"tpabr":"mu","cdabr":"78859","carper":13,"t":1,"f":"s","dv":"s","esae":"n","mnae":"","v":15}