{"ele":8707,"cdabr":"28630","nmabr":"SÃO BRÁS","t":1,"f":"S","s":"N","dg":"13/10/2020","hg":"20:04:41","v":"005","br":{"nm":"Brasil","uf":[{"sg":"AL","nm":"ALAGOAS","mun":[{"cd":"28630","nm":"SÃO BRÁS","c":"N","s":17,"e":5904,"tzon":1,"zon":[{"cd":"0037","s":17,"e":5904}]}]}]},"carg":{"cd":11,"nmn":"Prefeito","nmm":"Prefeito","nmf":"Prefeita","nv":0,"col":[{"n":20000281308,"nm":"COLIGACAO 20000281308","tp":"P","com":"P12","par":[{"n":12,"sg":" P12 ","nm":"PARTIDO 12","cand":[{"sqcand":20002342054,"n":12,"nm":"CANDIDATO 12","nmu":"CANDIDATO 12","s":"M","dt":"19/09/1929","dvt":"Válido","vs":[{"sqcand":20002342055,"nm":"CANDIDATO 12 1","nmu":"CANDIDATO 12 1","tp":"V","sgp":"P12"}]}]}]},{"n":20000281304,"nm":"COLIGACAO 20000281304","tp":"P","com":"P16","par":[{"n":16,"sg":" P16 ","nm":"PARTIDO 16","cand":[{"sqcand":20002342046,"n":16,"nm":"CANDIDATO 16","nmu":"CANDIDATO 16","s":"M","dt":"10/11/1929","dvt":"Válido","vs":[{"sqcand":20002342047,"nm":"CANDIDATO 16 1","nmu":"CANDIDATO 16 1","tp":"V","sgp":"P16"}]}]}]}]}}