{"dt":"11/11/2020","ht":"17:24:51","tf":"s","s":216,"st":216,"pst":" 100,00","snt":0,"psnt":"   0,00","si":216,"psi":" 100,00","sni":0,"psni":"   0,00","sa":216,"psa":" 100,00","sna":0,"psna":"   0,00","e":73275,"ea":73275,"pea":" 100,00","ena":0,"pena":"   0,00","esi":73275,"pesi":" 100,00","esni":0,"pesni":"   0,00","c":62398,"pc":"  85,16","a":10877,"pa":"  14,84","tv":62398,"vvc":45107,"pvvc":"  72,29","vscv":0,"vb":10621,"pvb":"  17,02","tvn":6670,"ptvn":"  10,69","vn":6670,"pvn":" 100,00","vnt":0,"pvnt":"   0,00","vp":0,"pvp":"   0,00","vv":45107,"pvv":" 100,00","van":0,"pvan":"   0,00","vansj":0,"pvansj":"   0,00","vnom":45107,"pvnom":" 100,00","cand":[{"seq":3,"sqcand":140000007454,"n":56,"nm":"CANDIDATO 56","cc":"P56 - P13 / P11 / P41 /  P56 / P24 / P78 / P52 / P15 / P34 / P21 / P44 / P71 / P37** / P20 / P18 / P23 / P32 / P14","nv":"CANDIDATO 56 1","e":"n","vap":7727,"pvap":"  17,13","st":"Não eleito","dvt":"Válido"},{"seq":4,"sqcand":140000018175,"n":16,"nm":"CANDIDATO 16","cc":"P16 - P55 / P66 / P16","nv":"CANDIDATO 16 1","e":"n","vap":7688,"pvap":"  17,04","st":"Não eleito","dvt":"Válido"},{"seq":6,"sqcand":140000005539,"n":17,"nm":"CANDIDATO 17","cc":"P17","nv":"CANDIDATO 17 1","e":"n","vap":5986,"pvap":"  13,27","st":"Não eleito","dvt":"Válido"},{"seq":1,"sqcand":140000014503,"n":51,"nm":"CANDIDATO 51","cc":"P51","nv":"CANDIDATO 51 1","e":"s","vap":8646,"pvap":"  19,17","st":"Eleito","dvt":"Válido"},{"seq":2,"sqcand":140000011710,"n":45,"nm":"CANDIDATO 45","cc":"P45","nv":"CANDIDATO 45 1","e":"n","vap":7755,"pvap":"  17,19","st":"Não eleito","dvt":"Válido"},{"seq":5,"sqcand":140000019214,"n":46,"nm":"CANDIDATO 46","cc":"P46 -  P46 / P26 / P28 / P29 / P12 / P37","nv":"CANDIDATO 46 1","e":"n","vap":7305,"pvap":"  16,19","st":"Não eleito","dvt":"Válido"}],"ele":8334,"tpabr":"mu","cdabr":"04642","carper":11,"t":1,"f":"s","dv":"s","esae":"n","mnae":"","v":1}