{"ele":8707,"carper":13,"t":1,"f":"S","esae":"N","mnae":" ","dg":"13/10/2020","hg":"20:12:07","dv":"S","nadf":"pe25313-c0013-e008707-006-f","abr":[{"dt":"10/10/2020","ht":"10:16:56","tf":"S","and":"F","s":4304,"st":4304,"pst":" 100,00","snt":0,"psnt":"   0,00","si":4304,"psi":" 100,00","sni":0,"psni":"   0,00","sa":4304,"psa":" 100,00","sna":0,"psna":"   0,00","e":1402817,"ea":1402817,"pea":" 100,00","ena":0,"pena":"   0,00","esi":1402817,"pesi":" 100,00","esni":0,"pesni":"   0,00","c":1190725,"pc":"  84,88","a":212092,"pa":"  15,12","tv":1190725,"vscv":0,"vb":49116,"pvb":"   4,13","tvn":52451,"ptvn":"   4,40","vn":52451,"pvn":" 100,00","vnt":0,"pvnt":"   0,00","vp":0,"pvp":"   0,00","vv":1089158,"pvv":" 100,00","vl":106818,"pvl":"   9,81","van":0,"pvan":"   0,00","vansj":0,"pvansj":"   0,00","vnom":982340,"pvnom":"  90,19","cand":[{"seq":5,"n":41008,"e":"S","vap":50772,"pvap":"   4,26","st":"Eleito"},{"seq":11,"n":41005,"e":"N","vap":49564,"pvap":"   4,16","st":"Suplente"},{"seq":14,"n":41002,"e":"N","vap":48483,"pvap":"   4,07","st":"Suplente"},{"seq":15,"n":41006,"e":"N","vap":48083,"pvap":"   4,04","st":"Suplente"},{"seq":9,"n":41009,"e":"S","vap":49590,"pvap":"   4,16","st":"Eleito"},{"seq":6,"n":41010,"e":"S","vap":50347,"pvap":"   4,23","st":"Eleito"},{"seq":7,"n":41001,"e":"S","vap":50185,"pvap":"   4,21","st":"Eleito"},{"seq":19,"n":41003,"e":"N","vap":44598,"pvap":"   3,75","st":"Suplente"},{"seq":20,"n":41004,"e":"N","vap":43927,"pvap":"   3,69","st":"Suplente"},{"seq":3,"n":41007,"e":"S","vap":51985,"pvap":"   4,37","st":"Eleito"},{"seq":18,"n":28008,"e":"N","vap":45735,"pvap":"   3,84","st":"Suplente"},{"seq":12,"n":28003,"e":"N","vap":48744,"pvap":"   4,09","st":"Suplente"},{"seq":16,"n":28002,"e":"N","vap":47851,"pvap":"   4,02","st":"Suplente"},{"seq":2,"n":28007,"e":"S","vap":52632,"pvap":"   4,42","st":"Eleito"},{"seq":8,"n":28001,"e":"S","vap":49898,"pvap":"   4,19","st":"Eleito"},{"seq":4,"n":28006,"e":"S","vap":51718,"pvap":"   4,34","st":"Eleito"},{"seq":1,"n":28004,"e":"S","vap":54141,"pvap":"   4,55","st":"Eleito"},{"seq":10,"n":28010,"e":"S","vap":49166,"pvap":"   4,13","st":"Eleito"},{"seq":13,"n":28005,"e":"N","vap":48495,"pvap":"   4,07","st":"Suplente"},{"seq":17,"n":28009,"e":"N","vap":46426,"pvap":"   3,90","st":"Suplente"}],"tpabr":"MU","cdabr":"25313","colig":[{"n":170000249805,"tvtn":487534,"tvtl":583825,"tvan":487534,"tval":583825,"vag":5},{"n":170000249804,"tvtn":494806,"tvtl":591173,"tvan":494806,"tval":591173,"vag":5}],"part":[{"n":41,"tvtn":487534,"tvtl":583825,"tvan":487534,"tval":583825},{"n":28,"tvtn":494806,"tvtl":591173,"tvan":494806,"tval":591173}]},{"dt":"10/10/2020","ht":"10:16:56","tf":"S","and":"F","s":304,"st":304,"pst":" 100,00","snt":0,"psnt":"0","si":304,"psi":" 100,00","sni":0,"psni":"   0,00","sa":304,"psa":" 100,00","sna":0,"psna":"   0,00","e":105165,"ea":105165,"pea":" 100,00","ena":0,"pena":"   0,00","esi":105165,"pesi":" 100,00","esni":0,"pesni":"   0,00","c":89213,"pc":"  84,83","a":15952,"pa":"  15,17","tv":89213,"vscv":0,"vb":3492,"pvb":"   3,91","tvn":4477,"ptvn":"   5,02","vn":4477,"pvn":" 100,00","vp":0,"pvp":"   0,00","vv":81244,"pvv":" 100,00","vl":7527,"pvl":"   9,26","van":0,"pvan":"   0,00","vansj":0,"pvansj":"   0,00","vnom":73717,"pvnom":"  90,74","cand":[{"seq":5,"n":41008,"e":"S","vap":3643,"pvap":"   4,08","st":"Eleito"},{"seq":11,"n":41005,"e":"N","vap":3337,"pvap":"   3,74","st":"Suplente"},{"seq":14,"n":41002,"e":"N","vap":3171,"pvap":"   3,55","st":"Suplente"},{"seq":15,"n":41006,"e":"N","vap":4137,"pvap":"   4,64","st":"Suplente"},{"seq":6,"n":41010,"e":"S","vap":2956,"pvap":"   3,31","st":"Eleito"},{"seq":9,"n":41009,"e":"S","vap":3848,"pvap":"   4,31","st":"Eleito"},{"seq":19,"n":41003,"e":"N","vap":4394,"pvap":"   4,93","st":"Suplente"},{"seq":7,"n":41001,"e":"S","vap":2580,"pvap":"   2,89","st":"Eleito"},{"seq":20,"n":41004,"e":"N","vap":3294,"pvap":"   3,69","st":"Suplente"},{"seq":3,"n":41007,"e":"S","vap":5449,"pvap":"   6,11","st":"Eleito"},{"seq":18,"n":28008,"e":"N","vap":3251,"pvap":"   3,64","st":"Suplente"},{"seq":12,"n":28003,"e":"N","vap":2420,"pvap":"   2,71","st":"Suplente"},{"seq":2,"n":28007,"e":"S","vap":4160,"pvap":"   4,66","st":"Eleito"},{"seq":8,"n":28001,"e":"S","vap":4436,"pvap":"   4,97","st":"Eleito"},{"seq":16,"n":28002,"e":"N","vap":3748,"pvap":"   4,20","st":"Suplente"},{"seq":4,"n":28006,"e":"S","vap":4404,"pvap":"   4,94","st":"Eleito"},{"seq":1,"n":28004,"e":"S","vap":4556,"pvap":"   5,11","st":"Eleito"},{"seq":10,"n":28010,"e":"S","vap":3236,"pvap":"   3,63","st":"Eleito"},{"seq":13,"n":28005,"e":"N","vap":4090,"pvap":"   4,58","st":"Suplente"},{"seq":17,"n":28009,"e":"N","vap":2607,"pvap":"   2,92","st":"Suplente"}],"tpabr":"ZONA","cdabr":"6"},{"dt":"10/10/2020","ht":"10:16:56","tf":"S","and":"F","s":298,"st":298,"pst":" 100,00","snt":0,"psnt":"0","si":298,"psi":" 100,00","sni":0,"psni":"   0,00","sa":298,"psa":" 100,00","sna":0,"psna":"   0,00","e":103444,"ea":103444,"pea":" 100,00","ena":0,"pena":"   0,00","esi":103444,"pesi":" 100,00","esni":0,"pesni":"   0,00","c":87859,"pc":"  84,93","a":15585,"pa":"  15,07","tv":87859,"vscv":0,"vb":2952,"pvb":"   3,36","tvn":3975,"ptvn":"   4,52","vn":3975,"pvn":" 100,00","vp":0,"pvp":"   0,00","vv":80932,"pvv":" 100,00","vl":7503,"pvl":"   9,27","van":0,"pvan":"   0,00","vansj":0,"pvansj":"   0,00","vnom":73429,"pvnom":"  90,73","cand":[{"seq":18,"n":28008,"e":"N","vap":4342,"pvap":"   4,94","st":"Suplente"},{"seq":12,"n":28003,"e":"N","vap":5104,"pvap":"   5,81","st":"Suplente"},{"seq":8,"n":28001,"e":"S","vap":3037,"pvap":"   3,46","st":"Eleito"},{"seq":16,"n":28002,"e":"N","vap":3368,"pvap":"   3,83","st":"Suplente"},{"seq":2,"n":28007,"e":"S","vap":3373,"pvap":"   3,84","st":"Eleito"},{"seq":1,"n":28004,"e":"S","vap":4346,"pvap":"   4,95","st":"Eleito"},{"seq":4,"n":28006,"e":"S","vap":5283,"pvap":"   6,01","st":"Eleito"},{"seq":10,"n":28010,"e":"S","vap":3299,"pvap":"   3,75","st":"Eleito"},{"seq":13,"n":28005,"e":"N","vap":2454,"pvap":"   2,79","st":"Suplente"},{"seq":17,"n":28009,"e":"N","vap":4482,"pvap":"   5,10","st":"Suplente"},{"seq":5,"n":41008,"e":"S","vap":4082,"pvap":"   4,65","st":"Eleito"},{"seq":14,"n":41002,"e":"N","vap":2348,"pvap":"   2,67","st":"Suplente"},{"seq":11,"n":41005,"e":"N","vap":2959,"pvap":"   3,37","st":"Suplente"},{"seq":15,"n":41006,"e":"N","vap":4214,"pvap":"   4,80","st":"Suplente"},{"seq":6,"n":41010,"e":"S","vap":3538,"pvap":"   4,03","st":"Eleito"},{"seq":9,"n":41009,"e":"S","vap":3314,"pvap":"   3,77","st":"Eleito"},{"seq":19,"n":41003,"e":"N","vap":2848,"pvap":"   3,24","st":"Suplente"},{"seq":7,"n":41001,"e":"S","vap":4325,"pvap":"   4,92","st":"Eleito"},{"seq":20,"n":41004,"e":"N","vap":3397,"pvap":"   3,87","st":"Suplente"},{"seq":3,"n":41007,"e":"S","vap":3316,"pvap":"   3,77","st":"Eleito"}],"tpabr":"ZONA","cdabr":"7"},{"dt":"10/10/2020","ht":"10:16:56","tf":"S","and":"F","s":799,"st":799,"pst":" 100,00","snt":0,"psnt":"0","si":799,"psi":" 100,00","sni":0,"psni":"   0,00","sa":799,"psa":" 100,00","sna":0,"psna":"   0,00","e":234323,"ea":234323,"pea":" 100,00","ena":0,"pena":"   0,00","esi":234323,"pesi":" 100,00","esni":0,"pesni":"   0,00","c":198942,"pc":"  84,90","a":35381,"pa":"  15,10","tv":198942,"vscv":0,"vb":9965,"pvb":"   5,01","tvn":8079,"ptvn":"   4,06","vn":8079,"pvn":" 100,00","vp":0,"pvp":"   0,00","vv":180898,"pvv":" 100,00","vl":16667,"pvl":"   9,21","van":0,"pvan":"   0,00","vansj":0,"pvansj":"   0,00","vnom":164231,"pvnom":"  90,79","cand":[{"seq":5,"n":41008,"e":"S","vap":8226,"pvap":"   4,13","st":"Eleito"},{"seq":11,"n":41005,"e":"N","vap":8222,"pvap":"   4,13","st":"Suplente"},{"seq":14,"n":41002,"e":"N","vap":8477,"pvap":"   4,26","st":"Suplente"},{"seq":15,"n":41006,"e":"N","vap":7537,"pvap":"   3,79","st":"Suplente"},{"seq":9,"n":41009,"e":"S","vap":9546,"pvap":"   4,80","st":"Eleito"},{"seq":6,"n":41010,"e":"S","vap":8664,"pvap":"   4,36","st":"Eleito"},{"seq":7,"n":41001,"e":"S","vap":8700,"pvap":"   4,37","st":"Eleito"},{"seq":19,"n":41003,"e":"N","vap":7380,"pvap":"   3,71","st":"Suplente"},{"seq":20,"n":41004,"e":"N","vap":6680,"pvap":"   3,36","st":"Suplente"},{"seq":3,"n":41007,"e":"S","vap":9391,"pvap":"   4,72","st":"Eleito"},{"seq":18,"n":28008,"e":"N","vap":8317,"pvap":"   4,18","st":"Suplente"},{"seq":12,"n":28003,"e":"N","vap":6456,"pvap":"   3,25","st":"Suplente"},{"seq":2,"n":28007,"e":"S","vap":9217,"pvap":"   4,63","st":"Eleito"},{"seq":16,"n":28002,"e":"N","vap":8505,"pvap":"   4,28","st":"Suplente"},{"seq":8,"n":28001,"e":"S","vap":8777,"pvap":"   4,41","st":"Eleito"},{"seq":1,"n":28004,"e":"S","vap":8562,"pvap":"   4,30","st":"Eleito"},{"seq":4,"n":28006,"e":"S","vap":8577,"pvap":"   4,31","st":"Eleito"},{"seq":10,"n":28010,"e":"S","vap":7337,"pvap":"   3,69","st":"Eleito"},{"seq":13,"n":28005,"e":"N","vap":7873,"pvap":"   3,96","st":"Suplente"},{"seq":17,"n":28009,"e":"N","vap":7787,"pvap":"   3,91","st":"Suplente"}],"tpabr":"ZONA","cdabr":"1"},{"dt":"10/10/2020","ht":"10:16:56","tf":"S","and":"F","s":725,"st":725,"pst":" 100,00","snt":0,"psnt":"0","si":725,"psi":" 100,00","sni":0,"psni":"   0,00","sa":725,"psa":" 100,00","sna":0,"psna":"   0,00","e":223627,"ea":223627,"pea":" 100,00","ena":0,"pena":"   0,00","esi":223627,"pesi":" 100,00","esni":0,"pesni":"   0,00","c":189594,"pc":"  84,78","a":34033,"pa":"  15,22","tv":189594,"vscv":0,"vb":6612,"pvb":"   3,49","tvn":9108,"ptvn":"   4,80","vn":9108,"pvn":" 100,00","vp":0,"pvp":"   0,00","vv":173874,"pvv":" 100,00","vl":15736,"pvl":"   9,05","van":0,"pvan":"   0,00","vansj":0,"pvansj":"   0,00","vnom":158138,"pvnom":"  90,95","cand":[{"seq":18,"n":28008,"e":"N","vap":6503,"pvap":"   3,43","st":"Suplente"},{"seq":12,"n":28003,"e":"N","vap":8881,"pvap":"   4,68","st":"Suplente"},{"seq":16,"n":28002,"e":"N","vap":8053,"pvap":"   4,25","st":"Suplente"},{"seq":2,"n":28007,"e":"S","vap":8165,"pvap":"   4,31","st":"Eleito"},{"seq":8,"n":28001,"e":"S","vap":8163,"pvap":"   4,31","st":"Eleito"},{"seq":1,"n":28004,"e":"S","vap":9159,"pvap":"   4,83","st":"Eleito"},{"seq":4,"n":28006,"e":"S","vap":8643,"pvap":"   4,56","st":"Eleito"},{"seq":10,"n":28010,"e":"S","vap":9090,"pvap":"   4,79","st":"Eleito"},{"seq":17,"n":28009,"e":"N","vap":6880,"pvap":"   3,63","st":"Suplente"},{"seq":13,"n":28005,"e":"N","vap":7443,"pvap":"   3,93","st":"Suplente"},{"seq":5,"n":41008,"e":"S","vap":7677,"pvap":"   4,05","st":"Eleito"},{"seq":14,"n":41002,"e":"N","vap":8299,"pvap":"   4,38","st":"Suplente"},{"seq":11,"n":41005,"e":"N","vap":8946,"pvap":"   4,72","st":"Suplente"},{"seq":15,"n":41006,"e":"N","vap":7247,"pvap":"   3,82","st":"Suplente"},{"seq":6,"n":41010,"e":"S","vap":8311,"pvap":"   4,38","st":"Eleito"},{"seq":9,"n":41009,"e":"S","vap":7887,"pvap":"   4,16","st":"Eleito"},{"seq":19,"n":41003,"e":"N","vap":7089,"pvap":"   3,74","st":"Suplente"},{"seq":7,"n":41001,"e":"S","vap":8357,"pvap":"   4,41","st":"Eleito"},{"seq":20,"n":41004,"e":"N","vap":6206,"pvap":"   3,27","st":"Suplente"},{"seq":3,"n":41007,"e":"S","vap":7139,"pvap":"   3,77","st":"Eleito"}],"tpabr":"ZONA","cdabr":"2"},{"dt":"10/10/2020","ht":"10:16:56","tf":"S","and":"F","s":309,"st":309,"pst":" 100,00","snt":0,"psnt":"0","si":309,"psi":" 100,00","sni":0,"psni":"   0,00","sa":309,"psa":" 100,00","sna":0,"psna":"   0,00","e":104533,"ea":104533,"pea":" 100,00","ena":0,"pena":"   0,00","esi":104533,"pesi":" 100,00","esni":0,"pesni":"   0,00","c":88752,"pc":"  84,90","a":15781,"pa":"  15,10","tv":88752,"vscv":0,"vb":4102,"pvb":"   4,62","tvn":3392,"ptvn":"   3,82","vn":3392,"pvn":" 100,00","vp":0,"pvp":"   0,00","vv":81258,"pvv":" 100,00","vl":7743,"pvl":"   9,53","van":0,"pvan":"   0,00","vansj":0,"pvansj":"   0,00","vnom":73515,"pvnom":"  90,47","cand":[{"seq":5,"n":41008,"e":"S","vap":3760,"pvap":"   4,24","st":"Eleito"},{"seq":14,"n":41002,"e":"N","vap":3945,"pvap":"   4,44","st":"Suplente"},{"seq":11,"n":41005,"e":"N","vap":3517,"pvap":"   3,96","st":"Suplente"},{"seq":15,"n":41006,"e":"N","vap":3186,"pvap":"   3,59","st":"Suplente"},{"seq":9,"n":41009,"e":"S","vap":2957,"pvap":"   3,33","st":"Eleito"},{"seq":6,"n":41010,"e":"S","vap":3363,"pvap":"   3,79","st":"Eleito"},{"seq":19,"n":41003,"e":"N","vap":2329,"pvap":"   2,62","st":"Suplente"},{"seq":7,"n":41001,"e":"S","vap":3919,"pvap":"   4,42","st":"Eleito"},{"seq":20,"n":41004,"e":"N","vap":3344,"pvap":"   3,77","st":"Suplente"},{"seq":3,"n":41007,"e":"S","vap":3844,"pvap":"   4,33","st":"Eleito"},{"seq":18,"n":28008,"e":"N","vap":4169,"pvap":"   4,70","st":"Suplente"},{"seq":12,"n":28003,"e":"N","vap":4240,"pvap":"   4,78","st":"Suplente"},{"seq":8,"n":28001,"e":"S","vap":4311,"pvap":"   4,86","st":"Eleito"},{"seq":2,"n":28007,"e":"S","vap":4590,"pvap":"   5,17","st":"Eleito"},{"seq":16,"n":28002,"e":"N","vap":4718,"pvap":"   5,32","st":"Suplente"},{"seq":1,"n":28004,"e":"S","vap":3069,"pvap":"   3,46","st":"Eleito"},{"seq":4,"n":28006,"e":"S","vap":3034,"pvap":"   3,42","st":"Eleito"},{"seq":10,"n":28010,"e":"S","vap":4040,"pvap":"   4,55","st":"Eleito"},{"seq":17,"n":28009,"e":"N","vap":3957,"pvap":"   4,46","st":"Suplente"},{"seq":13,"n":28005,"e":"N","vap":3223,"pvap":"   3,63","st":"Suplente"}],"tpabr":"ZONA","cdabr":"8"},{"dt":"10/10/2020","ht":"10:16:56","tf":"S","and":"F","s":333,"st":333,"pst":" 100,00","snt":0,"psnt":"0","si":333,"psi":" 100,00","sni":0,"psni":"   0,00","sa":333,"psa":" 100,00","sna":0,"psna":"   0,00","e":103162,"ea":103162,"pea":" 100,00","ena":0,"pena":"   0,00","esi":103162,"pesi":" 100,00","esni":0,"pesni":"   0,00","c":87692,"pc":"  85,00","a":15470,"pa":"  15,00","tv":87692,"vscv":0,"vb":4623,"pvb":"   5,27","tvn":3710,"ptvn":"   4,23","vn":3710,"pvn":" 100,00","vp":0,"pvp":"   0,00","vv":79359,"pvv":" 100,00","vl":9626,"pvl":"  12,13","van":0,"pvan":"   0,00","vansj":0,"pvansj":"   0,00","vnom":69733,"pvnom":"  87,87","cand":[{"seq":18,"n":28008,"e":"N","vap":3076,"pvap":"   3,51","st":"Suplente"},{"seq":12,"n":28003,"e":"N","vap":3294,"pvap":"   3,76","st":"Suplente"},{"seq":8,"n":28001,"e":"S","vap":2640,"pvap":"   3,01","st":"Eleito"},{"seq":2,"n":28007,"e":"S","vap":3742,"pvap":"   4,27","st":"Eleito"},{"seq":16,"n":28002,"e":"N","vap":3303,"pvap":"   3,77","st":"Suplente"},{"seq":4,"n":28006,"e":"S","vap":3383,"pvap":"   3,86","st":"Eleito"},{"seq":1,"n":28004,"e":"S","vap":3004,"pvap":"   3,43","st":"Eleito"},{"seq":10,"n":28010,"e":"S","vap":4523,"pvap":"   5,16","st":"Eleito"},{"seq":13,"n":28005,"e":"N","vap":4669,"pvap":"   5,32","st":"Suplente"},{"seq":17,"n":28009,"e":"N","vap":3382,"pvap":"   3,86","st":"Suplente"},{"seq":5,"n":41008,"e":"S","vap":2624,"pvap":"   2,99","st":"Eleito"},{"seq":11,"n":41005,"e":"N","vap":3250,"pvap":"   3,71","st":"Suplente"},{"seq":14,"n":41002,"e":"N","vap":3757,"pvap":"   4,28","st":"Suplente"},{"seq":15,"n":41006,"e":"N","vap":3791,"pvap":"   4,32","st":"Suplente"},{"seq":9,"n":41009,"e":"S","vap":3338,"pvap":"   3,81","st":"Eleito"},{"seq":6,"n":41010,"e":"S","vap":3318,"pvap":"   3,78","st":"Eleito"},{"seq":19,"n":41003,"e":"N","vap":3235,"pvap":"   3,69","st":"Suplente"},{"seq":7,"n":41001,"e":"S","vap":3985,"pvap":"   4,54","st":"Eleito"},{"seq":20,"n":41004,"e":"N","vap":2315,"pvap":"   2,64","st":"Suplente"},{"seq":3,"n":41007,"e":"S","vap":5104,"pvap":"   5,82","st":"Eleito"}],"tpabr":"ZONA","cdabr":"4"},{"dt":"10/10/2020","ht":"10:16:56","tf":"S","and":"F","s":302,"st":302,"pst":" 100,00","snt":0,"psnt":"0","si":302,"psi":" 100,00","sni":0,"psni":"   0,00","sa":302,"psa":" 100,00","sna":0,"psna":"   0,00","e":105678,"ea":105678,"pea":" 100,00","ena":0,"pena":"   0,00","esi":105678,"pesi":" 100,00","esni":0,"pesni":"   0,00","c":89869,"pc":"  85,04","a":15809,"pa":"  14,96","tv":89869,"vscv":0,"vb":2544,"pvb":"   2,83","tvn":3682,"ptvn":"   4,10","vn":3682,"pvn":" 100,00","vp":0,"pvp":"   0,00","vv":83643,"pvv":" 100,00","vl":10150,"pvl":"  12,13","van":0,"pvan":"   0,00","vansj":0,"pvansj":"   0,00","vnom":73493,"pvnom":"  87,87","cand":[{"seq":5,"n":41008,"e":"S","vap":4063,"pvap":"   4,52","st":"Eleito"},{"seq":11,"n":41005,"e":"N","vap":3342,"pvap":"   3,72","st":"Suplente"},{"seq":14,"n":41002,"e":"N","vap":3822,"pvap":"   4,25","st":"Suplente"},{"seq":15,"n":41006,"e":"N","vap":3209,"pvap":"   3,57","st":"Suplente"},{"seq":6,"n":41010,"e":"S","vap":3358,"pvap":"   3,74","st":"Eleito"},{"seq":9,"n":41009,"e":"S","vap":4648,"pvap":"   5,17","st":"Eleito"},{"seq":7,"n":41001,"e":"S","vap":3431,"pvap":"   3,82","st":"Eleito"},{"seq":19,"n":41003,"e":"N","vap":4404,"pvap":"   4,90","st":"Suplente"},{"seq":20,"n":41004,"e":"N","vap":3403,"pvap":"   3,79","st":"Suplente"},{"seq":3,"n":41007,"e":"S","vap":4099,"pvap":"   4,56","st":"Eleito"},{"seq":18,"n":28008,"e":"N","vap":3279,"pvap":"   3,65","st":"Suplente"},{"seq":12,"n":28003,"e":"N","vap":3121,"pvap":"   3,47","st":"Suplente"},{"seq":8,"n":28001,"e":"S","vap":3996,"pvap":"   4,45","st":"Eleito"},{"seq":16,"n":28002,"e":"N","vap":3667,"pvap":"   4,08","st":"Suplente"},{"seq":2,"n":28007,"e":"S","vap":3758,"pvap":"   4,18","st":"Eleito"},{"seq":1,"n":28004,"e":"S","vap":5282,"pvap":"   5,88","st":"Eleito"},{"seq":4,"n":28006,"e":"S","vap":3654,"pvap":"   4,07","st":"Eleito"},{"seq":10,"n":28010,"e":"S","vap":2252,"pvap":"   2,51","st":"Eleito"},{"seq":13,"n":28005,"e":"N","vap":3945,"pvap":"   4,39","st":"Suplente"},{"seq":17,"n":28009,"e":"N","vap":2760,"pvap":"   3,07","st":"Suplente"}],"tpabr":"ZONA","cdabr":"5"},{"dt":"10/10/2020","ht":"10:16:56","tf":"S","and":"F","s":311,"st":311,"pst":" 100,00","snt":0,"psnt":"0","si":311,"psi":" 100,00","sni":0,"psni":"   0,00","sa":311,"psa":" 100,00","sna":0,"psna":"   0,00","e":105718,"ea":105718,"pea":" 100,00","ena":0,"pena":"   0,00","esi":105718,"pesi":" 100,00","esni":0,"pesni":"   0,00","c":89485,"pc":"  84,64","a":16233,"pa":"  15,36","tv":89485,"vscv":0,"vb":3053,"pvb":"   3,41","tvn":4026,"ptvn":"   4,50","vn":4026,"pvn":" 100,00","vp":0,"pvp":"   0,00","vv":82406,"pvv":" 100,00","vl":6988,"pvl":"   8,48","van":0,"pvan":"   0,00","vansj":0,"pvansj":"   0,00","vnom":75418,"pvnom":"  91,52","cand":[{"seq":5,"n":41008,"e":"S","vap":3582,"pvap":"   4,00","st":"Eleito"},{"seq":11,"n":41005,"e":"N","vap":5013,"pvap":"   5,60","st":"Suplente"},{"seq":14,"n":41002,"e":"N","vap":4204,"pvap":"   4,70","st":"Suplente"},{"seq":15,"n":41006,"e":"N","vap":4393,"pvap":"   4,91","st":"Suplente"},{"seq":9,"n":41009,"e":"S","vap":3481,"pvap":"   3,89","st":"Eleito"},{"seq":6,"n":41010,"e":"S","vap":5699,"pvap":"   6,37","st":"Eleito"},{"seq":7,"n":41001,"e":"S","vap":4579,"pvap":"   5,12","st":"Eleito"},{"seq":19,"n":41003,"e":"N","vap":3413,"pvap":"   3,81","st":"Suplente"},{"seq":20,"n":41004,"e":"N","vap":3868,"pvap":"   4,32","st":"Suplente"},{"seq":3,"n":41007,"e":"S","vap":2922,"pvap":"   3,27","st":"Eleito"},{"seq":18,"n":28008,"e":"N","vap":2729,"pvap":"   3,05","st":"Suplente"},{"seq":12,"n":28003,"e":"N","vap":3332,"pvap":"   3,72","st":"Suplente"},{"seq":2,"n":28007,"e":"S","vap":3283,"pvap":"   3,67","st":"Eleito"},{"seq":16,"n":28002,"e":"N","vap":3387,"pvap":"   3,78","st":"Suplente"},{"seq":8,"n":28001,"e":"S","vap":4084,"pvap":"   4,56","st":"Eleito"},{"seq":1,"n":28004,"e":"S","vap":3587,"pvap":"   4,01","st":"Eleito"},{"seq":4,"n":28006,"e":"S","vap":3049,"pvap":"   3,41","st":"Eleito"},{"seq":10,"n":28010,"e":"S","vap":3551,"pvap":"   3,97","st":"Eleito"},{"seq":13,"n":28005,"e":"N","vap":3666,"pvap":"   4,10","st":"Suplente"},{"seq":17,"n":28009,"e":"N","vap":3596,"pvap":"   4,02","st":"Suplente"}],"tpabr":"ZONA","cdabr":"3"},{"dt":"10/10/2020","ht":"10:16:56","tf":"S","and":"F","s":283,"st":283,"pst":" 100,00","snt":0,"psnt":"0","si":283,"psi":" 100,00","sni":0,"psni":"   0,00","sa":283,"psa":" 100,00","sna":0,"psna":"   0,00","e":103993,"ea":103993,"pea":" 100,00","ena":0,"pena":"   0,00","esi":103993,"pesi":" 100,00","esni":0,"pesni":"   0,00","c":88466,"pc":"  85,07","a":15527,"pa":"  14,93","tv":88466,"vscv":0,"vb":2331,"pvb":"   2,63","tvn":5056,"ptvn":"   5,72","vn":5056,"pvn":" 100,00","vp":0,"pvp":"   0,00","vv":81079,"pvv":" 100,00","vl":8440,"pvl":"  10,41","van":0,"pvan":"   0,00","vansj":0,"pvansj":"   0,00","vnom":72639,"pvnom":"  89,59","cand":[{"seq":18,"n":28008,"e":"N","vap":3529,"pvap":"   3,99","st":"Suplente"},{"seq":12,"n":28003,"e":"N","vap":4193,"pvap":"   4,74","st":"Suplente"},{"seq":16,"n":28002,"e":"N","vap":2766,"pvap":"   3,13","st":"Suplente"},{"seq":2,"n":28007,"e":"S","vap":4458,"pvap":"   5,04","st":"Eleito"},{"seq":8,"n":28001,"e":"S","vap":3298,"pvap":"   3,73","st":"Eleito"},{"seq":1,"n":28004,"e":"S","vap":5654,"pvap":"   6,39","st":"Eleito"},{"seq":4,"n":28006,"e":"S","vap":3790,"pvap":"   4,28","st":"Eleito"},{"seq":10,"n":28010,"e":"S","vap":4039,"pvap":"   4,57","st":"Eleito"},{"seq":17,"n":28009,"e":"N","vap":2636,"pvap":"   2,98","st":"Suplente"},{"seq":13,"n":28005,"e":"N","vap":2767,"pvap":"   3,13","st":"Suplente"},{"seq":5,"n":41008,"e":"S","vap":3641,"pvap":"   4,12","st":"Eleito"},{"seq":14,"n":41002,"e":"N","vap":2528,"pvap":"   2,86","st":"Suplente"},{"seq":11,"n":41005,"e":"N","vap":3812,"pvap":"   4,31","st":"Suplente"},{"seq":15,"n":41006,"e":"N","vap":4006,"pvap":"   4,53","st":"Suplente"},{"seq":6,"n":41010,"e":"S","vap":3239,"pvap":"   3,66","st":"Eleito"},{"seq":9,"n":41009,"e":"S","vap":3252,"pvap":"   3,68","st":"Eleito"},{"seq":7,"n":41001,"e":"S","vap":3485,"pvap":"   3,94","st":"Eleito"},{"seq":19,"n":41003,"e":"N","vap":3678,"pvap":"   4,16","st":"Suplente"},{"seq":20,"n":41004,"e":"N","vap":3802,"pvap":"   4,30","st":"Suplente"},{"seq":3,"n":41007,"e":"S","vap":4066,"pvap":"   4,60","st":"Eleito"}],"tpabr":"ZONA","cdabr":"9"},{"dt":"10/10/2020","ht":"10:16:56","tf":"S","and":"F","s":312,"st":312,"pst":" 100,00","snt":0,"psnt":"0","si":312,"psi":" 100,00","sni":0,"psni":"   0,00","sa":312,"psa":" 100,00","sna":0,"psna":"   0,00","e":107202,"ea":107202,"pea":" 100,00","ena":0,"pena":"   0,00","esi":107202,"pesi":" 100,00","esni":0,"pesni":"   0,00","c":90614,"pc":"  84,53","a":16588,"pa":"  15,47","tv":90614,"vscv":0,"vb":4742,"pvb":"   5,24","tvn":2875,"ptvn":"   3,17","vn":2875,"pvn":" 100,00","vp":0,"pvp":"   0,00","vv":82997,"pvv":" 100,00","vl":8871,"pvl":"  10,69","van":0,"pvan":"   0,00","vansj":0,"pvansj":"   0,00","vnom":74126,"pvnom":"  89,31","cand":[{"seq":5,"n":41008,"e":"S","vap":4046,"pvap":"   4,47","st":"Eleito"},{"seq":11,"n":41005,"e":"N","vap":3177,"pvap":"   3,51","st":"Suplente"},{"seq":14,"n":41002,"e":"N","vap":3726,"pvap":"   4,11","st":"Suplente"},{"seq":15,"n":41006,"e":"N","vap":3409,"pvap":"   3,76","st":"Suplente"},{"seq":9,"n":41009,"e":"S","vap":3506,"pvap":"   3,87","st":"Eleito"},{"seq":6,"n":41010,"e":"S","vap":4310,"pvap":"   4,76","st":"Eleito"},{"seq":7,"n":41001,"e":"S","vap":3792,"pvap":"   4,18","st":"Eleito"},{"seq":19,"n":41003,"e":"N","vap":2529,"pvap":"   2,79","st":"Suplente"},{"seq":20,"n":41004,"e":"N","vap":3462,"pvap":"   3,82","st":"Suplente"},{"seq":3,"n":41007,"e":"S","vap":3647,"pvap":"   4,02","st":"Eleito"},{"seq":18,"n":28008,"e":"N","vap":3173,"pvap":"   3,50","st":"Suplente"},{"seq":12,"n":28003,"e":"N","vap":3397,"pvap":"   3,75","st":"Suplente"},{"seq":16,"n":28002,"e":"N","vap":3939,"pvap":"   4,35","st":"Suplente"},{"seq":8,"n":28001,"e":"S","vap":3789,"pvap":"   4,18","st":"Eleito"},{"seq":2,"n":28007,"e":"S","vap":4815,"pvap":"   5,31","st":"Eleito"},{"seq":4,"n":28006,"e":"S","vap":3515,"pvap":"   3,88","st":"Eleito"},{"seq":1,"n":28004,"e":"S","vap":3368,"pvap":"   3,72","st":"Eleito"},{"seq":10,"n":28010,"e":"S","vap":4212,"pvap":"   4,65","st":"Eleito"},{"seq":17,"n":28009,"e":"N","vap":4096,"pvap":"   4,52","st":"Suplente"},{"seq":13,"n":28005,"e":"N","vap":4218,"pvap":"   4,65","st":"Suplente"}],"tpabr":"ZONA","cdabr":"149"},{"dt":"10/10/2020","ht":"10:16:56","tf":"S","and":"F","s":328,"st":328,"pst":" 100,00","snt":0,"psnt":"0","si":328,"psi":" 100,00","sni":0,"psni":"   0,00","sa":328,"psa":" 100,00","sna":0,"psna":"   0,00","e":105972,"ea":105972,"pea":" 100,00","ena":0,"pena":"   0,00","esi":105972,"pesi":" 100,00","esni":0,"pesni":"   0,00","c":90239,"pc":"  85,15","a":15733,"pa":"  14,85","tv":90239,"vscv":0,"vb":4700,"pvb":"   5,21","tvn":4071,"ptvn":"   4,51","vn":4071,"pvn":" 100,00","vp":0,"pvp":"   0,00","vv":81468,"pvv":" 100,00","vl":7567,"pvl":"   9,29","van":0,"pvan":"   0,00","vansj":0,"pvansj":"   0,00","vnom":73901,"pvnom":"  90,71","cand":[{"seq":18,"n":28008,"e":"N","vap":3367,"pvap":"   3,73","st":"Suplente"},{"seq":12,"n":28003,"e":"N","vap":4306,"pvap":"   4,77","st":"Suplente"},{"seq":16,"n":28002,"e":"N","vap":2397,"pvap":"   2,66","st":"Suplente"},{"seq":8,"n":28001,"e":"S","vap":3367,"pvap":"   3,73","st":"Eleito"},{"seq":2,"n":28007,"e":"S","vap":3071,"pvap":"   3,40","st":"Eleito"},{"seq":4,"n":28006,"e":"S","vap":4386,"pvap":"   4,86","st":"Eleito"},{"seq":1,"n":28004,"e":"S","vap":3554,"pvap":"   3,94","st":"Eleito"},{"seq":10,"n":28010,"e":"S","vap":3587,"pvap":"   3,97","st":"Eleito"},{"seq":13,"n":28005,"e":"N","vap":4147,"pvap":"   4,60","st":"Suplente"},{"seq":17,"n":28009,"e":"N","vap":4243,"pvap":"   4,70","st":"Suplente"},{"seq":5,"n":41008,"e":"S","vap":5428,"pvap":"   6,02","st":"Eleito"},{"seq":14,"n":41002,"e":"N","vap":4206,"pvap":"   4,66","st":"Suplente"},{"seq":11,"n":41005,"e":"N","vap":3989,"pvap":"   4,42","st":"Suplente"},{"seq":15,"n":41006,"e":"N","vap":2954,"pvap":"   3,27","st":"Suplente"},{"seq":6,"n":41010,"e":"S","vap":3591,"pvap":"   3,98","st":"Eleito"},{"seq":9,"n":41009,"e":"S","vap":3813,"pvap":"   4,23","st":"Eleito"},{"seq":7,"n":41001,"e":"S","vap":3032,"pvap":"   3,36","st":"Eleito"},{"seq":19,"n":41003,"e":"N","vap":3299,"pvap":"   3,66","st":"Suplente"},{"seq":20,"n":41004,"e":"N","vap":4156,"pvap":"   4,61","st":"Suplente"},{"seq":3,"n":41007,"e":"S","vap":3008,"pvap":"   3,33","st":"Eleito"}],"tpabr":"ZONA","cdabr":"150"}]}